Workbook

Sheet Executive Summary
A1: MAVERICK SPEND CONVERSION TRACKER
A2: Did non-contract (maverick) Exhibit B spend move onto an awarded contract? | January 5, 2026 to August 20, 2026
B4: THE BOTTOM LINE
B5: Of 175 distinct sourcing efforts representing $53,461,392 of Exhibit B spend, 8 can be independently verified as having moved onto an awarded contract during the period. Departments self-reported 33 as awarded. The gap between the claim and the evidence is the single most important finding in this analysis.
B9: CONVERSION SCORECARD
B10: Measure | C10: Requisitions | D10: Spend | E10: Basis
B11: Total Exhibit B spend in period | C11: =COUNTA('EB Detail'!$A$2:$A$731) | D11: =SUM('EB Detail'!$F$2:$F$731) | E11: Every Exhibit B requisition in the source file
B12: Expected to convert (new contract requested) | C12: =COUNTIF('EB Detail'!$W$2:$W$731,"Yes") | D12: =SUMIF('EB Detail'!$W$2:$W$731,"Yes",'EB Detail'!$F$2:$F$731) | E12: Excludes one-time purchases, invoice reconciliation, bid protests
B13: Self-reported by department as awarded | C13: =COUNTIF('EB Detail'!$K$2:$K$731,"Yes") | D13: =SUMIF('EB Detail'!$K$2:$K$731,"Yes",'EB Detail'!$F$2:$F$731) | E13: Department's own 'Contract Awarded?' answer - unverified
B14: VERIFIED converted to an awarded contract | C14: =COUNTIF('EB Detail'!$U$2:$U$731,"Yes") | D14: =SUMIF('EB Detail'!$U$2:$U$731,"Yes",'EB Detail'!$F$2:$F$731) | E14: ID or vendor+commodity link to the awarded file, award dated after the Exhibit B
B15: of which COMPETITIVELY awarded (Bid/RFQ/RFP) | C15: =COUNTIFS('EB Detail'!$U$2:$U$731,"Yes",'EB Detail'!$T$2:$T$731,"Yes") | D15: =SUMIFS('EB Detail'!$F$2:$F$731,'EB Detail'!$U$2:$U$731,"Yes",'EB Detail'!$T$2:$T$731,"Yes") | E15: The procurement-correct outcome
B16: of which non-competitive (sole source/emergency) | C16: =COUNTIFS('EB Detail'!$U$2:$U$731,"Yes",'EB Detail'!$T$2:$T$731,"No") | D16: =SUMIFS('EB Detail'!$F$2:$F$731,'EB Detail'!$U$2:$U$731,"Yes",'EB Detail'!$T$2:$T$731,"No") | E16: Exited Exhibit B but did NOT go competitive
B17: Reverse leakage (Exhibit B filed AFTER award) | C17: =COUNTIF('EB Detail'!$V$2:$V$731,"Yes") | D17: =SUMIF('EB Detail'!$V$2:$V$731,"Yes",'EB Detail'!$F$2:$F$731) | E17: Contract existed - spend should have ridden it
B18: Still open / no linkage found | C18: =COUNTIF('EB Detail'!$N$2:$N$731,"E") | D18: =SUMIF('EB Detail'!$N$2:$N$731,"E",'EB Detail'!$F$2:$F$731) | E18: No matching award in the supplied file - see Limitations
B20: CONVERSION RATE
B21: Verified conversion rate - requisitions, as % of those expected to convert | C21: =IFERROR(COUNTIFS('EB Detail'!$W$2:$W$731,"Yes",'EB Detail'!$U$2:$U$731,"Yes")/C12,0)
B22: Verified conversion rate - dollars, as % of spend expected to convert | C22: =IFERROR(SUMIFS('EB Detail'!$F$2:$F$731,'EB Detail'!$W$2:$W$731,"Yes",'EB Detail'!$U$2:$U$731,"Yes")/D12,0)
B23: Competitive conversion rate - dollars, as % of spend expected to convert | C23: =IFERROR(SUMIFS('EB Detail'!$F$2:$F$731,'EB Detail'!$W$2:$W$731,"Yes",'EB Detail'!$U$2:$U$731,"Yes",'EB Detail'!$T$2:$T$731,"Yes")/D12,0)
B24: Department claims that verify (of rows marked 'Contract Awarded? = Yes') | C24: =IFERROR(COUNTIFS('EB Detail'!$K$2:$K$731,"Yes",'EB Detail'!$U$2:$U$731,"Yes")/COUNTIF('EB Detail'!$K$2:$K$731,"Yes"),0)
B25: Verified conversions the department did NOT flag as awarded | C25: =COUNTIFS('EB Detail'!$K$2:$K$731,"No",'EB Detail'!$U$2:$U$731,"Yes")
B27: WHAT LEADERSHIP NEEDS TO KNOW
B28: 1. The claim does not survive verification
B29: Departments marked 48 requisitions ($9,997,088) as having an awarded contract. Only 6 of those verify against the awarded contract file. Of the 25 contract numbers departments supplied, only 2 appear anywhere in the actual award data. The error runs both ways: 16 requisitions did convert to an awarded contract but were never flagged as awarded. Exhibit B status is not being maintained.
B32: 2. Exhibit B spend is concentrated in a handful of stalled sourcing efforts
B33: The single largest - There was an active contract for Comprehensive Custodial Services for Zones 1, 2, and 4, w - accounts for $16,275,951 across 49 requisitions and is still in 'A. Specification Development Phase'. Counting requisitions instead of sourcing efforts hides this.
B36: 3. Near-term relief is real and measurable
B37: 25 requisitions worth $8,587,385 sit in Recommendation of Award or Signature Cycle - one step from contract. These convert in the next 60-90 days without new intervention.
B40: 4. The long tail will not clear this year
B41: 357 requisitions worth $23,024,247 are still in Specification Development. On normal cycle times these are 12+ months from award and will keep generating Exhibit B activity.
B44: 5. Exiting Exhibit B is not the same as going competitive
B45: Of the awarded contracts in this period, only 53 of 100 were competitively procured (Bid/RFQ/RFP). Some Exhibit B spend exited into sole-source and emergency awards - off the exception report, but not competitively sourced.
B48: 6. Reverse leakage is occurring
B49: 8 requisitions were filed as Exhibit B exceptions AFTER a contract had already been awarded for that scope. That spend should have ridden the contract.

Sheet Conversion Scorecard
A1: CONVERSION SCORECARD BY SOURCING EFFORT
A2: One row per distinct sourcing effort (the pending new-contract requisition), not per Exhibit B requisition. This is the correct unit of analysis.
A4: Sourcing Effort | B4: Description | C4: Lead Department | D4: Exhibit B Vendor | E4: Requisitions | F4: Depts | G4: Exhibit B Spend | H4: Procurement Phase | I4: Status | J4: Evidence Tier | K4: Awarded Contract | L4: Award Type
A5: RX624331 | B5: There was an active contract for Comprehensive Custodial Services for Zones 1, 2, and 4, which expire on February 13, 2026. 2FM previously submitted a | C5: DEPARTMENT OF FLEET AND FACILITY MANAGEMENT | D5: ABM INDUSTRY GROUPS, LLC | E5: 49 | F5: 2 | G5: 16275951 | H5: A. Specification Development Phase | I5: Still open | J5: E
A6: VDALDRIDGE ELECTRIC | B6: PO 96175 Aldridge Electric Exhibit B $3,900,000.00 | C6: CHICAGO DEPARTMENT OF TRANSPORTATION | D6: ALDRIDGE ELECTRIC INC | E6: 1 | F6: 1 | G6: 3900000 | H6: E. ROA - (Recommendation of Award) | I6: Claimed awarded - UNVERIFIED | J6: E
A7: RX686938 | B7: Transfered from APRF No. 511278. Regular and emergency bus services at O'Hare Airport for January through March 2026 | C7: CHICAGO DEPARTMENT OF AVIATION | D7: DELAWARE CARS/T.R. HARMSEN CORP. J.V. | E7: 1 | F7: 1 | G7: 3276126.9 | H7: F. SC - (Signature Cycle) | I7: Still open | J7: E
A8: RX661351 | B8: Liquid Aluminum Sulfate (Iron Free) | C8: DEPARTMENT OF WATER MANAGEMENT | D8: USALCO | E8: 7 | F8: 1 | G8: 3248945.8 | H8: A. Specification Development Phase | I8: Still open | J8: E
A9: RX604388 | B9: Transfered from APRF No. 513665. Requesting a Direct Voucher - Exhibit B for O'Hare due to expired contract. Elevators,1-MOD/Final 7/27/26 nt | C9: CHICAGO DEPARTMENT OF AVIATION | D9: SCHINDLER ELEVATOR CORP | E9: 3 | F9: 1 | G9: 2596967.8 | H9: D. Solicitation Response Under Evaluation | I9: Still open | J9: E
A10: RX634792 | B10: PURCHASE OF BLACK AND BLUE MOBILE CARTS | C10: DEPARTMENT OF STREETS AND SANITATION | D10: CASCADE ENGINEERING, INC | E10: 4 | F10: 1 | G10: 2406381.5 | H10: C. Solicitation or Bidding Phase | I10: Still open | J10: E
A11: RX492778 | B11: Street and Parkway Restoration Central North Region | C11: DEPARTMENT OF WATER MANAGEMENT | D11: SUMIT CONSTRUCTION CO., INC. | E11: 2 | F11: 1 | G11: 1902848.1 | H11: H. One Time Purchase | I11: Claimed awarded - UNVERIFIED | J11: C | K11: 385131 | L11: BID
A12: RX596048 | B12: FFIB Industrial Fence $578,668.60 | C12: CHICAGO FIRE DEPARTMENT | D12: INDUSTRIAL FENCE INC. | E12: 22 | F12: 3 | G12: 1061040.1 | H12: B. City Law Review | I12: Still open | J12: E
A13: RX492777 | B13: Street and Parkway Restoration North Region | C13: DEPARTMENT OF WATER MANAGEMENT | D13: SUMIT CONSTRUCTION CO., INC. | E13: 1 | F13: 1 | G13: 938950.36 | H13: H. One Time Purchase | I13: Claimed awarded - UNVERIFIED | J13: C | K13: 385131 | L13: BID
A14: RX650171 | B14: PROVIDE AN ELECTRICIANCUSTOMER, TROUBLESHOOTACCURPRESS AND BACK GAUGE FOROPERATION | C14: CHICAGO DEPARTMENT OF TRANSPORTATION | D14: PALM ELECTRIC COMPANY | E14: 10 | F14: 3 | G14: 891296.67 | H14: B. City Law Review | I14: Still open | J14: E
A15: RX682957 | B15: There is currently no active contract for Integrated Pest Management. The vendor chose not to extend beyond the May 29, 2025 expiration date. 2FM subm | C15: DEPARTMENT OF FLEET AND FACILITY MANAGEMENT | D15: ABC Humane Wildlife Control & Prevention, Inc. | E15: 21 | F15: 2 | G15: 824511.78 | H15: A. Specification Development Phase | I15: Still open | J15: E
A16: RX492772 | B16: Street and Parkway and Restoration Project No. 19-623 Central South Region | C16: DEPARTMENT OF WATER MANAGEMENT | D16: MAT CONSTRUCTION | E16: 1 | F16: 1 | G16: 687712.68 | H16: H. One Time Purchase | I16: Claimed awarded - UNVERIFIED | J16: E
A17: VDPALM ELECTRIC | B17: Invoice# I1257961 | C17: CHICAGO DEPARTMENT OF AVIATION | D17: PALM ELECTRIC COMPANY | E17: 1 | F17: 1 | G17: 684760.97 | H17: C. Solicitation or Bidding Phase | I17: Still open | J17: E
A18: RX590958 | B18: WB/MM/INVOICE#598412/$1221.66 | C18: DEPARTMENT OF FLEET AND FACILITY MANAGEMENT | D18: JACOB PRESS' SONS INC | E18: 35 | F18: 1 | G18: 678952.98 | H18: B. City Law Review | I18: Still open | J18: E
A19: VDATLAS TECHNICAL CONSULTANTS | B19: PO 114541 Exhibit B for Atlas Technical Consultants LLC | C19: CHICAGO DEPARTMENT OF TRANSPORTATION | D19: Atlas Technical Consultants LLC | E19: 1 | F19: 1 | G19: 503441.06 | H19: G. Not Applicable (Office Depot use Only) | I19: Claimed awarded - UNVERIFIED | J19: E
A20: RX425669 | B20: R4 Services / JK / EJ / INV # A410397 / $42,446.68 / June 2026 | C20: DEPARTMENT OF FLEET AND FACILITY MANAGEMENT | D20: R4 SERVICES, LLC. | E20: 8 | F20: 1 | G20: 484042.33 | H20: E. ROA - (Recommendation of Award) | I20: Still open | J20: E
A21: RX690281 | B21: TB/AH/10 INVOICES/$348,811.34 | C21: DEPARTMENT OF FLEET AND FACILITY MANAGEMENT | D21: SPEEDY GONZALEZ LANDSCAPING INC | E21: 5 | F21: 1 | G21: 460263.55 | H21: C. Solicitation or Bidding Phase | I21: Still open | J21: E
A22: VDARLINGTON GLASS MIRROR | B22: #5 Invoices $242,660.23 Transferred from APRF No. 505880. Replace broken glass at Rotunda, H&R plant, T3 UL vestibule 3H, and bullet resistant pMOD | C22: CHICAGO DEPARTMENT OF AVIATION | D22: ARLINGTON GLASS & MIRROR | E22: 3 | F22: 1 | G22: 456128.15 | H22: B. City Law Review | I22: Still open | J22: E
A23: VDP R STREICH SONS | B23: Transferred from APRF No. 511689. ONE TIME PURCHASE OF TWENTY-FOUR (24) MOBILE COLUMN HOISTS WITH EXTENSION KITS1-MOD/Final 4/16/26 kf | C23: CHICAGO DEPARTMENT OF AVIATION | D23: P. R. STREICH & SONS | E23: 2 | F23: 1 | G23: 404724.23 | H23: H. One Time Purchase | I23: Still open | J23: E
A24: RX693525 | B24: VARIOUS STREET SIGN MAKING SUPPLIES | C24: CHICAGO DEPARTMENT OF TRANSPORTATION | D24: RI-DEL MFG. INC. | E24: 4 | F24: 1 | G24: 383274.22 | H24: A. Specification Development Phase | I24: Still open | J24: E
A25: RX596443 | B25: Landscape Maintenance Services | C25: CHICAGO DEPARTMENT OF TRANSPORTATION | D25: A SAFE HAVEN FOUNDATION | E25: 9 | F25: 2 | G25: 380345.75 | H25: B. City Law Review | I25: Still open | J25: E
A26: VDFLOWERS COMMUNICATIONS | B26: Emergency Preparedness Kits | C26: CHICAGO DEPARTMENT OF PUBLIC HEALTH | D26: FLOWERS COMMUNICATIONS GROUP | E26: 3 | F26: 1 | G26: 372418 | H26: H. One Time Purchase | I26: Still open | J26: E
A27: RX493564 | B27: Sewer Construction | C27: DEPARTMENT OF WATER MANAGEMENT | D27: RELIABLE CONTRACTING AND EQUIPMENT COMPANY | E27: 1 | F27: 1 | G27: 363157.77 | H27: H. One Time Purchase | I27: Still open | J27: C | K27: 383808 | L27: BID
A28: RX607835 | B28: Current Spec 127930's Scope of services for this Exhibit B is outside of the current contract. Additional language was added to the new Specification | C28: DEPARTMENT OF FLEET AND FACILITY MANAGEMENT | D28: WISS, JANNEY, ELSTNER, & ASSOCIATES, INC. | E28: 7 | F28: 1 | G28: 353043.77 | H28: H. One Time Purchase | I28: Still open | J28: E
A29: RX605613 | B29: Invoice# 5332152783 Maintenance of the Supervisory Monitoring System & Fire Alarm System for October 2025 Monthly Service | C29: CHICAGO DEPARTMENT OF AVIATION | D29: SIEMENS INDUSTRY INC. 01 | E29: 1 | F29: 1 | G29: 347623.41 | H29: E. ROA - (Recommendation of Award) | I29: Claimed awarded - UNVERIFIED | J29: E
A30: RX511569 | B30: WATER - DRINKING | C30: DEPARTMENT OF STREETS AND SANITATION | D30: BLUETRITON BRANDS INC | E30: 9 | F30: 2 | G30: 331645.87 | H30: A. Specification Development Phase | I30: Claimed awarded - UNVERIFIED | J30: E
A31: RX746444 | B31: TARP - SALT TARPING | C31: DEPARTMENT OF STREETS AND SANITATION | D31: CHICAGO UNITED INDUSTRIES, LTD | E31: 1 | F31: 1 | G31: 327473.06 | H31: A. Specification Development Phase | I31: Still open | J31: E
A32: VDELECTRONIC KNOWLEDGE INTERCH | B32: TIER 2 SUPPORT - QUANT 16 SERVICES | C32: CHICAGO DEPARTMENT OF PUBLIC HEALTH | D32: Electronic Knowledge Interchange | E32: 5 | F32: 1 | G32: 306000 | H32: H. One Time Purchase | I32: Still open | J32: E
A33: RX710856 | B33: TB/INV#9008/$13,057.00 | C33: DEPARTMENT OF FLEET AND FACILITY MANAGEMENT | D33: CAR WASH PARTNERS INC | E33: 34 | F33: 1 | G33: 287936.99 | H33: A. Specification Development Phase | I33: Still open | J33: E
A34: RX724184 | B34: Hastings Air-Energy 1033282 B JS/ JG/ Invoice No. O38604D105/ $56,691.64/ April / Exhaust System Maint | C34: DEPARTMENT OF FLEET AND FACILITY MANAGEMENT | D34: HASTINGS AIR ENERGY CONTROL | E34: 5 | F34: 1 | G34: 278751.49 | H34: A. Specification Development Phase | I34: Claimed awarded - UNVERIFIED | J34: E
A35: RX659422 | B35: BOARD UP SERVICES | C35: DEPARTMENT OF BUILDINGS | D35: A & D PROPERTY SERVICES, INC. | E35: 5 | F35: 1 | G35: 277500 | H35: A. Specification Development Phase | I35: Still open | J35: E
A36: RX608757 | B36: Omicron CityKey Annual Licensing | C36: OFFICE OF CITY CLERK | D36: OMICRON TECHNOLOGY SOLUTIONS LLC | E36: 3 | F36: 1 | G36: 263800.02 | H36: B. City Law Review | I36: Still open | J36: E
A37: RX628102 | B37: Bella Bagno Inc is removing and installing carpet at the Bucktown/Wicker Park Branch Library. The labor services are outside of the contract prevue, a | C37: DEPARTMENT OF FLEET AND FACILITY MANAGEMENT | D37: BELLA BAGNO INC | E37: 2 | F37: 1 | G37: 260516.76 | H37: D. Solicitation Response Under Evaluation | I37: Claimed awarded - UNVERIFIED | J37: E
A38: VDSUNBELT STAFFING | B38: Sunbelt Outstanding Invoices | C38: CHICAGO DEPARTMENT OF PUBLIC HEALTH | D38: SUNBELT STAFFING LLC | E38: 2 | F38: 1 | G38: 247286 | H38: F. SC - (Signature Cycle) | I38: Still open | J38: E
A39: RX622326 | B39: Perform 2025 annual planned maintenance on one Caterpillar chlorine emergency power generator and five MTU main plant power emergency generators | C39: DEPARTMENT OF WATER MANAGEMENT | D39: CHARLES EQUIPMENT ENERGY SYSTEMS LLC | E39: 17 | F39: 2 | G39: 231704.01 | H39: H. One Time Purchase | I39: Still open | J39: E
... A45: RX600854 | B45: There is currently no active contract for this type of paper. The items being purchased are not part of the current Murnane contract. The Department | C45: DEPARTMENT OF FLEET AND FACILITY MANAGEMENT | D45: MURNANE PAPER COMPANY | E45: 14 | F45: 3 | G45: 195550.45 | H45: A. Specification Development Phase | I45: Still open | J45: E
A46: RX663987 | B46: JK / CA / INV#6660-3816-1 / WO#2626297 | C46: DEPARTMENT OF FLEET AND FACILITY MANAGEMENT | D46: Boschung America, LLC | E46: 4 | F46: 1 | G46: 189750.66 | H46: B. City Law Review | I46: Claimed awarded - UNVERIFIED | J46: C | K46: 388473 | L46: REFERENCE CONTRACT
A47: RX647383 | B47: Arlington did not want to proceed with the contract extension unless they had their price increases. CDA put forth 3 price increases for 5% each. DPS | C47: DEPARTMENT OF FLEET AND FACILITY MANAGEMENT | D47: ARLINGTON GLASS & MIRROR | E47: 28 | F47: 1 | G47: 179178.83 | H47: A. Specification Development Phase | I47: Still open | J47: E
A48: RX713262 | B48: Volcanic Bike Inv-1333 $173,853 | C48: CHICAGO POLICE DEPARTMENT | D48: Volcanic Bikes | E48: 2 | F48: 1 | G48: 173853 | H48: B. City Law Review | I48: Still open | J48: E
A49: RX734541 | B49: BOARD UP SERVICES | C49: DEPARTMENT OF BUILDINGS | D49: A & D PROPERTY SERVICES, INC. | E49: 3 | F49: 1 | G49: 159600 | H49: C. Solicitation or Bidding Phase | I49: Still open | J49: E
A50: RX712876 | B50: City Sticker Design Services | C50: OFFICE OF CITY CLERK | D50: TAYLOR COMMUNICATIONS INC | E50: 5 | F50: 1 | G50: 156506.59 | H50: A. Specification Development Phase | I50: Still open | J50: E
A51: RX669621 | B51: CDA requesting authorization to pay Siemens Industry Inc PO #84871, per service's procured in 2025 under active contract. Contract reached their vendo | C51: CHICAGO DEPARTMENT OF AVIATION | D51: SIEMENS INDUSTRY INC. 01 | E51: 1 | F51: 1 | G51: 156240 | H51: E. ROA - (Recommendation of Award) | I51: Claimed awarded - UNVERIFIED | J51: E
A52: VDCSI 3000 CONSTRUCTION JV | B52: PO 180678 REL 295456 CSI 3000JV Exhibit B Invoice Reconciliation | C52: CHICAGO DEPARTMENT OF TRANSPORTATION | D52: CSI 3000 Construction JV LLC | E52: 1 | F52: 1 | G52: 156098.14 | H52: E. ROA - (Recommendation of Award) | I52: Claimed awarded - UNVERIFIED | J52: E
A53: RX690671 | B53: 2FM currently holds two helicopter maintenance contracts; however, the Bell 407 and 429 aircraft are not covered under either agreement due to a lack | C53: DEPARTMENT OF FLEET AND FACILITY MANAGEMENT | D53: Helicopters, Inc. | E53: 7 | F53: 1 | G53: 150773.81 | H53: B. City Law Review | I53: Converted - non-competitive award | J53: A | K53: 386844 | L53: EMERGENCY
A54: RX710994 | B54: TB/CC/INVOICE #3371/$4495.20 | C54: DEPARTMENT OF FLEET AND FACILITY MANAGEMENT | D54: C & C COMMUNICATIONS IL | E54: 23 | F54: 1 | G54: 148760.52 | H54: A. Specification Development Phase | I54: Still open | J54: E
A55: RX492769 | B55: Street and Parkway Repair Project NO. 19-625 North Region | C55: DEPARTMENT OF WATER MANAGEMENT | D55: SEVEN D CONSTRUCTION COMPANY | E55: 1 | F55: 1 | G55: 143357.36 | H55: H. One Time Purchase | I55: Claimed awarded - UNVERIFIED | J55: C | K55: 383513 | L55: BID
A56: VDCHRISTY WEBBER LANDSCAPES | B56: Landscaping Services Standalone Jackson Park 2026 | C56: CHICAGO DEPARTMENT OF TRANSPORTATION | D56: CHRISTY WEBBER LANDSCAPES | E56: 1 | F56: 1 | G56: 136608.73 | H56: B. City Law Review | I56: Still open | J56: E
A57: RX738666 | B57: Equipment Depot of Illinois, Inc. 50081462 G JS/ WW/ Invoice # 1300174268/ $136,232.00/2 DUA FUEL FORKLIFTS 900 E. 10RD | C57: DEPARTMENT OF FLEET AND FACILITY MANAGEMENT | D57: EQUIPMENT DEPOT OF ILLINOIS INC | E57: 1 | F57: 1 | G57: 136232 | H57: A. Specification Development Phase | I57: Still open | J57: E
A58: RX702002 | B58: Medical supplies for the animals housed at CACC | C58: CHICAGO ANIMAL CARE AND CONTROL | D58: MIDWEST VETERINARY SUPPLY, INC. | E58: 2 | F58: 1 | G58: 129282.77 | H58: A. Specification Development Phase | I58: Still open | J58: E
A59: VDPAN OCEANIC ENGINEERING | B59: Sewer Construction | C59: DEPARTMENT OF WATER MANAGEMENT | D59: PAN-OCEANIC ENGINEERING CO INC | E59: 1 | F59: 1 | G59: 121426.74 | H59: H. One Time Purchase | I59: Claimed awarded - UNVERIFIED | J59: E
A60: RX609670 | B60: Aps 82_Fitness Equipment Maintenance Project | C60: DEPARTMENT OF FAMILY AND SUPPORT SERVICES | D60: DIRECT FITNESS SOLUTIONS, LLC | E60: 2 | F60: 1 | G60: 120600 | H60: A. Specification Development Phase | I60: Still open | J60: E
A61: RX334841 | B61: Exhibit B Collins Engineers, Inc. PO 30193 $117,913.97 | C61: CHICAGO DEPARTMENT OF TRANSPORTATION | D61: COLLINS ENGINEERS INC | E61: 1 | F61: 1 | G61: 117913.97 | H61: H. One Time Purchase | I61: Claimed awarded - UNVERIFIED | J61: E
A62: RX362438 | B62: Mpox/HIV consulting | C62: CHICAGO DEPARTMENT OF PUBLIC HEALTH | D62: AVOQ LLC | E62: 1 | F62: 1 | G62: 115000 | H62: H. One Time Purchase | I62: Claimed awarded - UNVERIFIED | J62: E
A63: RX729906 | B63: Veterinary medical pharmaceuticals | C63: CHICAGO ANIMAL CARE AND CONTROL | D63: Wood Dale Pharmacy | E63: 4 | F63: 1 | G63: 112637.08 | H63: A. Specification Development Phase | I63: Still open | J63: E
A64: RX709555 | B64: Purchase and Delivery of Wooden Barricades | C64: DEPARTMENT OF STREETS AND SANITATION | D64: BARRICADE LITES, INC. | E64: 1 | F64: 1 | G64: 97204.1 | H64: A. Specification Development Phase | I64: Still open | J64: E
A65: RX729894 | B65: Cremation services for Animal Control. VLI and Time Extension entered. June 2026 Invoice. | C65: CHICAGO ANIMAL CARE AND CONTROL | D65: THE SAINT FRANCIS GROUP | E65: 2 | F65: 1 | G65: 93731.4 | H65: A. Specification Development Phase | I65: Claimed awarded - UNVERIFIED | J65: E
A66: RX679901 | B66: KB/MM/ INV#56736/ $693.39 | C66: DEPARTMENT OF FLEET AND FACILITY MANAGEMENT | D66: P. R. STREICH & SONS | E66: 16 | F66: 1 | G66: 92999.35 | H66: B. City Law Review | I66: Still open | J66: E
A67: VDLEGEND WHITE ANIMAL HEALTH | B67: ANIMAL CARE AND CONTROL SUPPLIES | C67: CHICAGO ANIMAL CARE AND CONTROL | D67: LEGEND & WHITE ANIMAL HEALTH | E67: 3 | F67: 1 | G67: 88485.04 | H67: A. Specification Development Phase | I67: Still open | J67: E
... A70: RX723748 | B70: Landscape Services North & South LSD | C70: CHICAGO DEPARTMENT OF TRANSPORTATION | D70: Yellowstone Landscape, Inc | E70: 1 | F70: 1 | G70: 76280.53 | H70: B. City Law Review | I70: Still open | J70: E
A71: VDGREATER ILLINOIS TITLE | B71: Greater Illinois Title Company Invoices from Nov 2025 to Dec 2025 | C71: DEPARTMENT OF PLANNING AND DEVELOPMENT | D71: GREATER ILLINOIS TITLE CO. INC. | E71: 4 | F71: 1 | G71: 74125 | I71: Still open | J71: E
A72: VDCDW GOVERNMENT | B72: 1 invoice for CDWG That was canceled by mistake after 2FM merged with IT and the PO invoice was cancel and was not paid. | C72: DEPARTMENT OF TECHNOLOGY AND INNOVATION | D72: CDW GOVERNMENT, LLC. | E72: 1 | F72: 1 | G72: 69919.94 | H72: H. One Time Purchase | I72: Still open | J72: E
A73: VDBOARD TRUSTEES UNIV ILLINOIS | B73: Community Services, (Testing and Vaccine Services) December 2025 | C73: CHICAGO DEPARTMENT OF PUBLIC HEALTH | D73: BOARD OF TRUSTEES OF THE UNIV. OF ILLINOIS | E73: 1 | F73: 1 | G73: 69415.23 | H73: A. Specification Development Phase | I73: Still open | J73: E
A74: RX696070 | B74: ELECTRICALPRODUCTS AND SUPPLIES | C74: CHICAGO DEPARTMENT OF TRANSPORTATION | D74: GRAYBAR ELECTRIC CO INC | E74: 1 | F74: 1 | G74: 69314.85 | H74: B. City Law Review | I74: Still open | J74: E
A75: RX700212 | B75: DCASE submitted a new contract request for RENTAL AND MAINTENANCE OF PORTABLE CHEMICAL TOILETS, SINKS, WASTE WATER BARRELS, PORTABLE WATERLESS HAND SA | C75: DEPARTMENT OF FLEET AND FACILITY MANAGEMENT | D75: Service Sanitation Inc. | E75: 10 | F75: 3 | G75: 68314.5 | H75: D. Solicitation Response Under Evaluation | I75: Converted - competitive award | J75: B | K75: 381051 | L75: BID
A76: VDBANDIT INDUSTRIES | B76: STUMP GRINDING | C76: DEPARTMENT OF STREETS AND SANITATION | D76: BANDIT INDUSTRIES, INC | E76: 2 | F76: 1 | G76: 68173.46 | H76: D. Solicitation Response Under Evaluation | I76: Still open | J76: E
A77: RX667061 | B77: EXHIBIT B - TALOGY PO 251333 INVOICES $67,689.70 | C77: DEPARTMENT OF HUMAN RESOURCES | D77: Talogy, LLC | E77: 1 | F77: 1 | G77: 67689.7 | H77: A. Specification Development Phase | I77: Claimed awarded - UNVERIFIED | J77: E
A78: RX724825 | B78: S&S Lead Dept. 2FM utilizes PO 92930 for the Purchase of Paint Products and Accessories. The contract expired on 3/7/25. S&S submitted a replaceme | C78: DEPARTMENT OF FLEET AND FACILITY MANAGEMENT | D78: RAE PRODUCTS & CHEMICALS CORP. | E78: 3 | F78: 1 | G78: 67075.71 | H78: A. Specification Development Phase | I78: Still open | J78: E
A79: RX698477 | B79: Chemical reagents and larvicideSurveillance fee | C79: CHICAGO DEPARTMENT OF PUBLIC HEALTH | D79: VECTOR DISEASE CONTROL INTERNATIONAL LLC | E79: 1 | F79: 1 | G79: 66126.92 | H79: H. One Time Purchase | I79: Still open | J79: E
A80: RX676831 | B80: BOTTLED DRINKING WATER, DISTILLED WATER & WATER COOLER RENTALS | C80: CHICAGO DEPARTMENT OF TRANSPORTATION | D80: BLUETRITON BRANDS INC | E80: 27 | F80: 5 | G80: 63682.14 | H80: A. Specification Development Phase | I80: Still open | J80: E
A81: RX605420 | B81: eBicycle purchase for Parking Enforcement Aides | C81: DEPARTMENT OF FINANCE | D81: Volcanic Bikes | E81: 1 | F81: 1 | G81: 61200 | H81: H. One Time Purchase | I81: Still open | J81: E
A82: VDCANON U S A | B82: PRINTING EQUIPMENT | C82: DEPARTMENT OF LAW | D82: CANON U.S.A., INC | E82: 1 | F82: 1 | G82: 60771.56 | H82: C. Solicitation or Bidding Phase | I82: Still open | J82: C | K82: 388093 | L82: CONTRACT ASSIGNMENT/TRANSFER
A83: VDRUSH UNIVERSITY MEDICAL CENT | B83: Community Testing, Infection Prevention | C83: CHICAGO DEPARTMENT OF PUBLIC HEALTH | D83: RUSH UNIVERSITY MEDICAL CENTER | E83: 2 | F83: 1 | G83: 60732.8 | H83: A. Specification Development Phase | I83: Still open | J83: E
A84: RX698916 | B84: Feb 2026 Waste Management Services at Midway. To pay Invoice # 55883 | C84: CHICAGO DEPARTMENT OF AVIATION | D84: WASTE MANAGEMENT - METRO 01 | E84: 2 | F84: 1 | G84: 58167.62 | H84: A. Specification Development Phase | I84: Still open | J84: E
A85: RX708700 | B85: TB/MM/2 INVOICES/$1353.00 | C85: DEPARTMENT OF FLEET AND FACILITY MANAGEMENT | D85: PRESSURE WASHING SYSTEMS | E85: 9 | F85: 1 | G85: 56232 | H85: A. Specification Development Phase | I85: Still open | J85: E
A86: RX677490 | B86: TB/GR/INV #6101269-0/$6272.00 | C86: DEPARTMENT OF FLEET AND FACILITY MANAGEMENT | D86: WAREHOUSE DIRECT, INC. | E86: 7 | F86: 1 | G86: 53447.92 | H86: A. Specification Development Phase | I86: Still open | J86: E
A87: RX691891 | B87: Vohne Liche Kennels Inv 21389 $50,059 | C87: CHICAGO POLICE DEPARTMENT | D87: VOHNE LICHE KENNELS INC | E87: 1 | F87: 1 | G87: 50059 | H87: A. Specification Development Phase | I87: Still open | J87: E
A88: RX607736 | B88: TB/AO/INVOICE #S3388-1/$418.50 | C88: DEPARTMENT OF FLEET AND FACILITY MANAGEMENT | D88: AGAE CONTRACTORS, INC. | E88: 24 | F88: 3 | G88: 48852.45 | H88: C. Solicitation or Bidding Phase | I88: Still open | J88: E
A89: VDDLT SOLUTIONS | B89: 1- 2025 unpaid DLT invoice for Oracle Active Data Guard Processor. This invoice was received after the Finance cutoff received date of 02/27/2026 | C89: DEPARTMENT OF TECHNOLOGY AND INNOVATION | D89: DLT SOLUTIONS LLC | E89: 1 | F89: 1 | G89: 48673.35 | H89: H. One Time Purchase | I89: Still open | J89: A | K89: 387728 | L89: JOINT PURCHASE
A90: VDCIS SUPPORT | B90: CIS Maintenance/Support-December | C90: CHICAGO DEPARTMENT OF PUBLIC HEALTH | D90: CIS Support, Inc. | E90: 8 | F90: 1 | G90: 46950 | H90: H. One Time Purchase | I90: Still open | J90: E
A91: RX624517 | B91: TB/GC/INV #189156/$45,500.00 | C91: DEPARTMENT OF FLEET AND FACILITY MANAGEMENT | D91: A.M. BUS COMPANY, INC. | E91: 1 | F91: 1 | G91: 45500 | H91: H. One Time Purchase | I91: Still open | J91: E
A92: RX606988 | B92: Waste Management 1040290 L JS/ VJ/ 2-INVOICES/ $11,477.36/ Mar Services/ | C92: DEPARTMENT OF FLEET AND FACILITY MANAGEMENT | D92: WASTE MANAGEMENT OF ILLINOIS | E92: 3 | F92: 1 | G92: 45141.92 | H92: B. City Law Review | I92: Still open | J92: E
A93: VDAVOQ | B93: January 2025 Consulting Services CDPH MPV/HIVFebruary 2025 Consulting Services CDPH MPV/HIV | C93: CHICAGO DEPARTMENT OF PUBLIC HEALTH | D93: AVOQ LLC | E93: 1 | F93: 1 | G93: 40000 | H93: H. One Time Purchase | I93: Still open | J93: E
A94: RX428355 | B94: VETERINARY CLEANING SUPPLIES | C94: CHICAGO ANIMAL CARE AND CONTROL | D94: MIDWEST VETERINARY SUPPLY, INC. | E94: 2 | F94: 1 | G94: 39554.51 | H94: B. City Law Review | I94: Still open | J94: E
A95: RX697238 | B95: Various Safety Equipment | C95: CHICAGO DEPARTMENT OF TRANSPORTATION | D95: AIR ONE EQUIPMENT INC | E95: 1 | F95: 1 | G95: 35226.55 | H95: B. City Law Review | I95: Still open | J95: E
A96: VDLANDMARK MANAGEMENT SOLUTION | B96: FLEET AND FACILITY MANAGEMENT ("2FM") IS THE LEAD DEPARTMENT FOR PO 32909 INTEGRATED PEST MANAGEMENT SERVICES, THROUGH ABC HUMANE WILDLIFE/LANDMARK PE | C96: DEPARTMENT OF WATER MANAGEMENT | D96: Landmark Management Solutions LLC. | E96: 1 | F96: 1 | G96: 34562.66 | H96: H. One Time Purchase | I96: Claimed awarded - UNVERIFIED | J96: E
A97: RX669739 | B97: Republic Services Inv# 005898442 | C97: CHICAGO POLICE DEPARTMENT | D97: REPUBLIC SERVICES INC | E97: 9 | F97: 1 | G97: 33940.73 | H97: A. Specification Development Phase | I97: Still open | J97: E
A98: VDSEBIS DIRECT | B98: Office of the City Clerk - Chicago Vehicle Stickers | C98: OFFICE OF CITY CLERK | D98: SEBIS DIRECT | E98: 4 | F98: 1 | G98: 32830.95 | H98: A. Specification Development Phase | I98: Still open | J98: E
A99: VDCLARITY PARTNERS | B99: HAN Maintenance and Support Services - June 2026 | C99: CHICAGO DEPARTMENT OF PUBLIC HEALTH | D99: CLARITY PARTNERS LLC | E99: 1 | F99: 1 | G99: 31978.33 | H99: H. One Time Purchase | I99: Still open | J99: E
A100: RX717990 | B100: TB/MM/4 INVOICES/$4019.00 | C100: DEPARTMENT OF FLEET AND FACILITY MANAGEMENT | D100: PRESSURE WASHING SYSTEMS | E100: 7 | F100: 1 | G100: 31723 | H100: B. City Law Review | I100: Still open | J100: E
A101: VDGOLDSTAR COMMUNICATION | B101: CDPH 2025 Vaccine Outreach and Anti-Tobacco Media Campaign Services. | C101: CHICAGO DEPARTMENT OF PUBLIC HEALTH | D101: GOLDSTAR COMMUNICATION | E101: 2 | F101: 1 | G101: 30476.25 | H101: H. One Time Purchase | I101: Still open | J101: E
A102: RX717298 | B102: TB/AO/2 INVOICES/$29,195.38 | C102: DEPARTMENT OF FLEET AND FACILITY MANAGEMENT | D102: ROOT BROS MFG & SUPPLY CO | E102: 1 | F102: 1 | G102: 29195.38 | H102: A. Specification Development Phase | I102: Still open | J102: C | K102: 376209 | L102: BID
A103: VDPEST MANAGEMENT SUPPLY | B103: Purchase of Rodenticide | C103: DEPARTMENT OF STREETS AND SANITATION | D103: PEST MANAGEMENT SUPPLY | E103: 1 | F103: 1 | G103: 28637.75 | H103: A. Specification Development Phase | I103: Still open | J103: E
A104: RX687026 | B104: Invoice# 112505 2026 Midway Deicing Materials - Magnesium Chloride 50lb bag. To pay invoice # 112505 | C104: CHICAGO DEPARTMENT OF AVIATION | D104: VALDES LLC | E104: 1 | F104: 1 | G104: 27965 | H104: A. Specification Development Phase | I104: Still open | J104: E
A105: RX529316 | B105: ZIPCAR 54117025 - C JS/ WW/ 10-INVS/ $1,943.08/ DECEMBER 2025 CHARGES | C105: DEPARTMENT OF FLEET AND FACILITY MANAGEMENT | D105: ZIPCAR INC | E105: 9 | F105: 1 | G105: 27515.51 | H105: B. City Law Review | I105: Still open | J105: E
A106: RX689540 | B106: TB/INV#11302025/$1770.00 | C106: DEPARTMENT OF FLEET AND FACILITY MANAGEMENT | D106: 5410 Car Wash LLC | E106: 4 | F106: 1 | G106: 24511.81 | H106: A. Specification Development Phase | I106: Still open | J106: E
A107: VDSANITATION | B107: Exhibit B_ 8160 | C107: DEPARTMENT OF FAMILY AND SUPPORT SERVICES | D107: Service Sanitation Inc. | E107: 3 | F107: 1 | G107: 23964 | H107: A. Specification Development Phase | I107: Claimed awarded - UNVERIFIED | J107: A | K107: 381051 | L107: BID
A108: VDBLUETRITON BRANDS | B108: water | C108: DEPARTMENT OF STREETS AND SANITATION | D108: BLUETRITON BRANDS INC | E108: 16 | F108: 3 | G108: 22188.54 | H108: D. Solicitation Response Under Evaluation | I108: Still open | J108: E
...

Sheet Confirmed Conversions
A1: CONFIRMED CONVERSIONS - EVIDENCE TRAIL
A2: Every row here is independently verified: linked to the awarded contract file by ID or vendor+commodity, with the award dated AFTER the Exhibit B request.
A4: Exhibit B Req# | B4: Exhibit B Date | C4: Department | D4: Description | E4: Exhibit B Spend | F4: Awarded Contract ID | G4: Awarded Vendor | H4: Award Date | I4: Procurement Type | J4: Competitive? | K4: Match Basis
A5: 728515 | B5: 46146 | C5: DEPARTMENT OF FLEET AND FACILITY MANAGEMENT | D5: 2FM currently holds two helicopter maintenance contracts; however, the Bell 407 and 429 aircraft are not covered under e | E5: 89734.76 | F5: 386844 | G5: Helicopters, Inc. | H5: 46203 | I5: EMERGENCY | J5: No | K5: Requisition ID link: Exhibit B new-contract RX = awarded REQ
A6: 718284 | B6: 46097 | C6: DEPARTMENT OF FLEET AND FACILITY MANAGEMENT | D6: 2FM currently holds two helicopter maintenance contracts, however the Bell 407s and 429 aircraft are not under either co | E6: 18935.29 | F6: 386844 | G6: Helicopters, Inc. | H6: 46203 | I6: EMERGENCY | J6: No | K6: Requisition ID link: Exhibit B new-contract RX = awarded REQ
A7: 710068 | B7: 46048 | C7: DEPARTMENT OF FLEET AND FACILITY MANAGEMENT | D7: Helicopter 10633647 A JS/ BJ/ 6-Invoices/ $18,010.22/ PD911Z/ WO 2603623/ ASR | E7: 18010.22 | F7: 386844 | G7: Helicopters, Inc. | H7: 46203 | I7: EMERGENCY | J7: No | K7: Requisition ID link: Exhibit B new-contract RX = awarded REQ
A8: 739971 | B8: 46216 | C8: CHICAGO DEPARTMENT OF AVIATION | D8: 3 Invoices forACCT#1750627 Weather Augment Forecasting Services: 210-00278025 Period: 3/1/2026-3/31/2026; 210-00267261 P | E8: 9315 | F8: 381309 | G8: MURRAY & TRETTEL INC | H8: 46229 | I8: BID | J8: Yes | K8: Requisition ID link: Exhibit B new-contract RX = awarded REQ
A9: 711517 | B9: 46052 | C9: DEPARTMENT OF FLEET AND FACILITY MANAGEMENT | D9: DCASE submitted a new contract request for RENTAL AND MAINTENANCE OF PORTABLE CHEMICAL TOILETS, SINKS, WASTE WATER BARRE | E9: 7750 | F9: 381051 | G9: Service Sanitation Inc. | H9: 46203 | I9: BID | J9: Yes | K9: Vendor match + commodity overlap (similarity 0.64)
A10: 711510 | B10: 46052 | C10: DEPARTMENT OF FLEET AND FACILITY MANAGEMENT | D10: DCASE submitted a new contract request for RENTAL AND MAINTENANCE OF PORTABLE CHEMICAL TOILETS, SINKS, WASTE WATER BARRE | E10: 6700 | F10: 381051 | G10: Service Sanitation Inc. | H10: 46203 | I10: BID | J10: Yes | K10: Vendor match + commodity overlap (similarity 0.64)
A11: 716858 | B11: 46080 | C11: DEPARTMENT OF WATER MANAGEMENT | D11: SERVICE SANTATION REQ#613315. DCASE IS THE LEAD DEPARTMENT AND THE REQ WAS SENT TO DPS FOR A new contract on 8/13/2024 ( | E11: 5917 | F11: 381051 | G11: Service Sanitation Inc. | H11: 46203 | I11: BID | J11: Yes | K11: Requisition ID link: Exhibit B new-contract RX = awarded REQ
A12: 738810 | B12: 46212 | C12: CHICAGO DEPARTMENT OF PUBLIC HEALTH | D12: Consulting Fee June 2026 | E12: 3819.14 | F12: 386925 | G12: INTEGRATED SOLUTIONS CONSULTING CORPORATION | H12: 46220 | I12: SOLE SOURCE | J12: No | K12: Requisition ID link: Exhibit B new-contract RX = awarded REQ
A13: 730529 | B13: 46161 | C13: DEPARTMENT OF FLEET AND FACILITY MANAGEMENT | D13: TB/MM/INVOICE #Q25143/$3458.74 | E13: 3458.74 | F13: 386844 | G13: Helicopters, Inc. | H13: 46203 | I13: EMERGENCY | J13: No | K13: Requisition ID link: Exhibit B new-contract RX = awarded REQ
A14: 734145 | B14: 46177 | C14: CHICAGO DEPARTMENT OF PUBLIC HEALTH | D14: Hosting Fee | E14: 2499 | F14: 386925 | G14: INTEGRATED SOLUTIONS CONSULTING CORPORATION | H14: 46220 | I14: SOLE SOURCE | J14: No | K14: Requisition ID link: Exhibit B new-contract RX = awarded REQ
A15: 716927 | B15: 46080 | C15: CHICAGO DEPARTMENT OF AVIATION | D15: #2 Invoices $2,394.34 2025 FAA 139 Regulatory Compliance- Annual calibration of 3 decelerometers and Chargers equipmen | E15: 2394.34 | F15: 375509 | G15: Halliday Technologies | H15: 46106 | I15: BID | J15: Yes | K15: Requisition ID link: Exhibit B new-contract RX = awarded REQ
A16: 722898 | B16: 46119 | C16: CHICAGO DEPARTMENT OF PUBLIC HEALTH | D16: Consulting Fee February 2026Hosting Fee: February 2026Hosting Fee: January 2026 | E16: 1890.66 | F16: 386925 | G16: INTEGRATED SOLUTIONS CONSULTING CORPORATION | H16: 46220 | I16: SOLE SOURCE | J16: No | K16: Requisition ID link: Exhibit B new-contract RX = awarded REQ
... A26: 707665 | B26: 46058 | C26: CHICAGO DEPARTMENT OF AVIATION | D26: #4 Invoices $10,558.002025 Midway Snow Equipment & Snow Vehicles washing (Services 11/9, 11/10, 11/30 to 12/2 & 12/7 to | E26: 0 | F26: 375509 | G26: Halliday Technologies | H26: 46106 | I26: BID | J26: Yes | K26: Requisition ID link: Exhibit B new-contract RX = awarded REQ

Sheet Claimed vs Verified
A1: DEPARTMENT CLAIM vs INDEPENDENT VERIFICATION
A2: Rows the department marked 'Contract Awarded? = Yes'. The right-hand columns show what the awarded contract file actually supports.
A4: Exhibit B Req# | B4: Department | C4: Description | D4: Exhibit B Spend | E4: Contract # Claimed | F4: Claimed Number Check | G4: Evidence Tier | H4: Verdict | I4: Match Basis
A5: 730356 | B5: CHICAGO DEPARTMENT OF TRANSPORTATION | C5: PO 96175 Aldridge Electric Exhibit B $3,900,000.00 | D5: 3900000 | E5: Yes | F5: No number supplied | G5: E | H5: No supporting evidence | I5: No linkage found in awarded contract file
A6: 733323 | B6: DEPARTMENT OF WATER MANAGEMENT | C6: Street and Parkway Restoration cental North Region | D6: 1887067.6 | E6: 304519 | F6: NOT in award file | G6: C | H6: Weak / partial evidence | I6: Vendor name match only (similarity 0.00)
A7: 733294 | B7: DEPARTMENT OF WATER MANAGEMENT | C7: Street and Parkway Restoration North Region | D7: 938950.36 | E7: 305303 | F7: NOT in award file | G7: C | H7: Weak / partial evidence | I7: Vendor name match only (similarity 0.00)
A8: 734489 | B8: DEPARTMENT OF WATER MANAGEMENT | C8: Street and Parkway and Restoration Project No. 19-623 Central South Region | D8: 687712.68 | E8: 272862 | F8: NOT in award file | G8: E | H8: No supporting evidence | I8: No linkage found in awarded contract file
A9: 721945 | B9: CHICAGO DEPARTMENT OF TRANSPORTATION | C9: PO 114541 Exhibit B for Atlas Technical Consultants LLC | D9: 503441.06 | E9: 114541 | F9: NOT in award file | G9: E | H9: No supporting evidence | I9: No linkage found in awarded contract file
A10: 708701 | B10: CHICAGO DEPARTMENT OF AVIATION | C10: Invoice# 5332152783 Maintenance of the Supervisory Monitoring System & Fire Alarm System for October 2025 Mont | D10: 347623.41 | E10: 84871 | F10: NOT in award file | G10: E | H10: No supporting evidence | I10: No linkage found in awarded contract file
A11: 708713 | B11: CHICAGO DEPARTMENT OF AVIATION | C11: CDA requesting authorization to pay Siemens Industry Inc PO #84871, per service's procured in 2025 under activ | D11: 156240 | E11: 84871 | F11: NOT in award file | G11: E | H11: No supporting evidence | I11: No linkage found in awarded contract file
A12: 744818 | B12: CHICAGO DEPARTMENT OF TRANSPORTATION | C12: PO 180678 REL 295456 CSI 3000JV Exhibit B Invoice Reconciliation | D12: 156098.14 | E12: 309536 | F12: NOT in award file | G12: E | H12: No supporting evidence | I12: No linkage found in awarded contract file
A13: 738075 | B13: DEPARTMENT OF FLEET AND FACILITY MANAGEMENT | C13: Bella Bagno Inc is removing and installing carpet at the Bucktown/Wicker Park Branch Library. The labor servic | D13: 147666.41 | F13: No number supplied | G13: E | H13: No supporting evidence | I13: No linkage found in awarded contract file
A14: 734966 | B14: DEPARTMENT OF WATER MANAGEMENT | C14: Street and Parkway Repair Project NO. 19-625 North Region | D14: 143357.36 | E14: 272860 | F14: NOT in award file | G14: C | H14: Weak / partial evidence | I14: Vendor name match only (similarity 0.00)
A15: 737798 | B15: DEPARTMENT OF WATER MANAGEMENT | C15: Sewer Construction | D15: 121426.74 | E15: 297413 | F15: NOT in award file | G15: E | H15: No supporting evidence | I15: No linkage found in awarded contract file
A16: 725483 | B16: CHICAGO DEPARTMENT OF TRANSPORTATION | C16: Exhibit B Collins Engineers, Inc. PO 30193 $117,913.97 | D16: 117913.97 | E16: 319103 | F16: NOT in award file | G16: E | H16: No supporting evidence | I16: No linkage found in awarded contract file
A17: 710618 | B17: CHICAGO DEPARTMENT OF PUBLIC HEALTH | C17: Mpox/HIV consulting | D17: 115000 | E17: 225759 | F17: NOT in award file | G17: E | H17: No supporting evidence | I17: No linkage found in awarded contract file
A18: 707827 | B18: DEPARTMENT OF FLEET AND FACILITY MANAGEMENT | C18: Bella Bagno 1010329 D JS/ AO/ Invoice 130069/$ 112,850.35/ WO 5244306/ Legler | D18: 112850.35 | E18: Not awarded yet, still under DPS review. | F18: No number supplied | G18: E | H18: No supporting evidence | I18: No linkage found in awarded contract file
A19: 737175 | B19: CHICAGO ANIMAL CARE AND CONTROL | C19: VLI NEEDED FOR DEAD ANIMAL CREMATION SERVICES | D19: 80585.4 | E19: yes | F19: No number supplied | G19: E | H19: No supporting evidence | I19: No linkage found in awarded contract file
A20: 730922 | B20: DEPARTMENT OF FLEET AND FACILITY MANAGEMENT | C20: HASTINGS 1033282 B JS/ JG/ Invoice # O38604D104/ $78,693.06/ March/ Exhaust System Maint | D20: 78693.06 | E20: 112351 | F20: NOT in award file | G20: E | H20: No supporting evidence | I20: No linkage found in awarded contract file
A21: 727149 | B21: DEPARTMENT OF FLEET AND FACILITY MANAGEMENT | C21: Hastings 1033282 B JS/ JG/ Invoice # O38604D103/ $71,534.69/ February / Exhaust System Maintenance | D21: 71534.69 | E21: 112351 | F21: NOT in award file | G21: E | H21: No supporting evidence | I21: No linkage found in awarded contract file
A22: 711549 | B22: DEPARTMENT OF HUMAN RESOURCES | C22: EXHIBIT B - TALOGY PO 251333 INVOICES $67,689.70 | D22: 67689.7 | E22: 251333 | F22: NOT in award file | G22: E | H22: No supporting evidence | I22: No linkage found in awarded contract file
A23: 733531 | B23: DEPARTMENT OF FLEET AND FACILITY MANAGEMENT | C23: Hastings Air-Energy 1033282 B JS/ JG/ Invoice No. O38604D105/ $56,691.64/ April / Exhaust System Maint | D23: 56691.64 | E23: 112351 | F23: NOT in award file | G23: E | H23: No supporting evidence | I23: No linkage found in awarded contract file
A24: 741917 | B24: DEPARTMENT OF FLEET AND FACILITY MANAGEMENT | C24: 2FM has an active contract for Plymovent Exhaust Extraction Systems, PO 112351. 2FM submitted a request to ext | D24: 36953.65 | E24: 112351 | F24: NOT in award file | G24: E | H24: No supporting evidence | I24: No linkage found in awarded contract file
A25: 746580 | B25: DEPARTMENT OF FLEET AND FACILITY MANAGEMENT | C25: JK / CA / INV#6660-3816-1 / WO#2626297 | D25: 36815.66 | F25: No number supplied | G25: C | H25: Weak / partial evidence | I25: Vendor name match only (similarity 0.00)
A26: 746117 | B26: DEPARTMENT OF FLEET AND FACILITY MANAGEMENT | C26: TB/JG/INVOICE #O38604D106/$34,878.45 | D26: 34878.45 | E26: 112351 | F26: NOT in award file | G26: E | H26: No supporting evidence | I26: No linkage found in awarded contract file
A27: 719021 | B27: DEPARTMENT OF WATER MANAGEMENT | C27: FLEET AND FACILITY MANAGEMENT ("2FM") IS THE LEAD DEPARTMENT FOR PO 32909 INTEGRATED PEST MANAGEMENT SERVICES, | D27: 34562.66 | E27: 682957 | F27: NOT in award file | G27: E | H27: No supporting evidence | I27: No linkage found in awarded contract file
A28: 711554 | B28: DEPARTMENT OF HUMAN RESOURCES | C28: EXHIBIT B - MEDICAL/PHYSICAL EXAMS AND DRUG TESTING/LAB SERVICES - OCCUPATIONAL HEALTH CENTERS DBA CONCENTRA I | D28: 20353 | E28: 121696 | F28: NOT in award file | G28: E | H28: No supporting evidence | I28: No linkage found in awarded contract file
A29: 718284 | B29: DEPARTMENT OF FLEET AND FACILITY MANAGEMENT | C29: 2FM currently holds two helicopter maintenance contracts, however the Bell 407s and 429 aircraft are not under | D29: 18935.29 | E29: TBD | F29: No number supplied | G29: A | H29: VERIFIED | I29: Requisition ID link: Exhibit B new-contract RX = awarded REQ
A30: 710068 | B30: DEPARTMENT OF FLEET AND FACILITY MANAGEMENT | C30: Helicopter 10633647 A JS/ BJ/ 6-Invoices/ $18,010.22/ PD911Z/ WO 2603623/ ASR | D30: 18010.22 | E30: TBD | F30: No number supplied | G30: A | H30: VERIFIED | I30: Requisition ID link: Exhibit B new-contract RX = awarded REQ
A31: 733996 | B31: DEPARTMENT OF WATER MANAGEMENT | C31: Street and Parkway Restoration Central North Region | D31: 15780.52 | E31: 304519 | F31: NOT in award file | G31: C | H31: Weak / partial evidence | I31: Vendor name match only (similarity 0.07)
A32: 742847 | B32: CHICAGO DEPARTMENT OF TRANSPORTATION | C32: 31st Street Viaduct over Metra/ICRR - Exhibit B payment request for AECOM (PO #47573 - Rel 5) | D32: 13656.95 | E32: 47573 | F32: NOT in award file | G32: E | H32: No supporting evidence | I32: No linkage found in awarded contract file
A33: 746507 | B33: DEPARTMENT OF FAMILY AND SUPPORT SERVICES | C33: Exhibit B_$9865 | D33: 9865 | E33: 53096 | F33: NOT in award file | G33: E | H33: No supporting evidence | I33: No linkage found in awarded contract file
A34: 742855 | B34: DEPARTMENT OF FAMILY AND SUPPORT SERVICES | C34: Exhibit B_2 8160 | D34: 8160 | E34: 348927 | F34: Found in award file | G34: A | H34: Weak / partial evidence | I34: Contract number link: reported number = awarded PO
A35: 742832 | B35: DEPARTMENT OF FAMILY AND SUPPORT SERVICES | C35: Exhibit B_ 8160 | D35: 8160 | E35: 348927 | F35: Found in award file | G35: A | H35: Weak / partial evidence | I35: Contract number link: reported number = awarded PO
A36: 742887 | B36: DEPARTMENT OF FAMILY AND SUPPORT SERVICES | C36: Exhibit B_3_7644 | D36: 7644 | E36: 348927 | F36: Found in award file | G36: A | H36: Weak / partial evidence | I36: Contract number link: reported number = awarded PO
A37: 714146 | B37: DEPARTMENT OF WATER MANAGEMENT | C37: DCASE IS THE LEAD DEPARTMENT. REQ#613315 WAS SUBMITTED TO DPS ON 8/13/2024 FOR A NEW CONTRACT (BOARD DATE:09/1 | D37: 6427 | E37: 613315 | F37: Found in award file | G37: C | H37: Weak / partial evidence | I37: Vendor name match only (similarity 0.00)
A38: 718031 | B38: DEPARTMENT OF WATER MANAGEMENT | C38: A REQ#700212 HAS SUBMITED TO DPS FOR 181-DAY EXTENSION AND IS PENDING DOCUSIGN APPROVAL AS OF 2/9/26. A NEW CO | D38: 6325 | E38: 700212 | F38: NOT in award file | G38: C | H38: Weak / partial evidence | I38: Vendor name match only (similarity 0.00)
A39: 714112 | B39: DEPARTMENT OF WATER MANAGEMENT | C39: THIS SERVICE SANITATION ORDER NEEDED A NEW CONTRACT FOR THE PREVIOUS ONE HAS EXPIRED AND HAD BEEN WAITING FOR | D39: 6325 | E39: 613315 | F39: Found in award file | G39: C | H39: Weak / partial evidence | I39: Vendor name match only (similarity 0.00)
A40: 716858 | B40: DEPARTMENT OF WATER MANAGEMENT | C40: SERVICE SANTATION REQ#613315. DCASE IS THE LEAD DEPARTMENT AND THE REQ WAS SENT TO DPS FOR A new contract on 8 | D40: 5917 | E40: 613315 | F40: Found in award file | G40: A | H40: VERIFIED | I40: Requisition ID link: Exhibit B new-contract RX = awarded REQ
A41: 714132 | B41: CHICAGO DEPARTMENT OF PUBLIC HEALTH | C41: All In One Desktops | D41: 4815 | F41: No number supplied | G41: E | H41: No supporting evidence | I41: No linkage found in awarded contract file
A42: 722200 | B42: DEPARTMENT OF FLEET AND FACILITY MANAGEMENT | C42: Hastings 1033282 B JS/ JG/ Invoice Number: O38604D102-B/ $3,451.50/ January / Exhaust System Maint Pt. 2 | D42: 3451.5 | E42: 112351 | F42: NOT in award file | G42: E | H42: No supporting evidence | I42: No linkage found in awarded contract file
A43: 724291 | B43: DEPARTMENT OF HUMAN RESOURCES | C43: FRANK COONEY, INV# 7005, INVOICE DATE 2/18/26, AMOUNT $2,893.75 | D43: 2893.75 | E43: YES | F43: No number supplied | G43: E | H43: No supporting evidence | I43: No linkage found in awarded contract file
A44: 711685 | B44: DEPARTMENT OF FLEET AND FACILITY MANAGEMENT | C44: TB/JG/INV #COCL112025 / $1890.50 | D44: 1890.5 | E44: NO | F44: No number supplied | G44: E | H44: No supporting evidence | I44: No linkage found in awarded contract file
A45: 709848 | B45: DEPARTMENT OF FLEET AND FACILITY MANAGEMENT | C45: 2FM currently holds two helicopter maintenance contracts, however the Bell 407s and 429 aircraft are not under | D45: 1297.26 | E45: TBD | F45: No number supplied | G45: A | H45: VERIFIED | I45: Requisition ID link: Exhibit B new-contract RX = awarded REQ
A46: 712189 | B46: CHICAGO DEPARTMENT OF PUBLIC HEALTH | C46: Web Hosting fees - Storage fees | D46: 1006.4 | E46: 1209922/225755 | F46: NOT in award file | G46: E | H46: No supporting evidence | I46: No linkage found in awarded contract file
A47: 709600 | B47: DEPARTMENT OF FLEET AND FACILITY MANAGEMENT | C47: 2FM currently holds two helicopter maintenance contracts, however the Bell 407s and 429 aircraft are not under | D47: 840 | E47: TBD | F47: No number supplied | G47: A | H47: VERIFIED | I47: Requisition ID link: Exhibit B new-contract RX = awarded REQ
A48: 711660 | B48: DEPARTMENT OF FLEET AND FACILITY MANAGEMENT | C48: TB/JG/INV #COCL122025 / $580.98 | D48: 580.98 | E48: PO#130155 | F48: NOT in award file | G48: E | H48: No supporting evidence | I48: No linkage found in awarded contract file
A49: 708543 | B49: DEPARTMENT OF PROCUREMENT SERVICES | C49: MAINTENANCE AND REPAIR SERVICE ON TRUCK SCALES. - QUARTERLY TRUCK SCALE MAINTENANCE AND REPAIRS PER DETAILED S | D49: 450 | E49: 1424904 | F49: NOT in award file | G49: A | H49: VERIFIED | I49: Requisition ID link: Exhibit B new-contract RX = awarded REQ
A50: 741919 | B50: DEPARTMENT OF FLEET AND FACILITY MANAGEMENT | C50: CHICAGO UNITED 171076 / JK/ MM/ INVOICE #37743 / $424.32 | D50: 424.32 | E50: 291363 | F50: NOT in award file | G50: E | H50: No supporting evidence | I50: No linkage found in awarded contract file
A51: 731432 | B51: DEPARTMENT OF PROCUREMENT SERVICES | C51: Monthly Drinking Water Services at City of Chicago Salvage Operations May 2026 | D51: 96.18 | E51: 30043 | F51: NOT in award file | G51: E | H51: No supporting evidence | I51: No linkage found in awarded contract file
A52: 746334 | B52: DEPARTMENT OF PROCUREMENT SERVICES | C52: Monthly Drinking Water Services at City of Chicago Salvage Operations August 2026 | D52: 29.97 | E52: 30043 | F52: NOT in award file | G52: E | H52: No supporting evidence | I52: No linkage found in awarded contract file

Sheet Still Open - Ranked
A1: STILL-OPEN SOURCING EFFORTS RANKED BY SPEND AT RISK
A2: Maverick spend with no verified contract award. This is the work queue - clearing the top of this list removes the most Exhibit B activity.
A4: Rank | B4: Description | C4: Lead Department | D4: Requisitions | E4: Exhibit B Spend | F4: Cumulative | G4: Cum % | H4: Procurement Phase | I4: Status
A5: 1 | B5: There was an active contract for Comprehensive Custodial Services for Zones 1, 2, and 4, which expire on February 13, 2026. 2FM previously submitted a | C5: DEPARTMENT OF FLEET AND FACILITY MANAGEMENT | D5: 49 | E5: 16275951 | F5: 16275951 | G5: 0.30588548 | H5: A. Specification Development Phase | I5: Still open
A6: 2 | B6: PO 96175 Aldridge Electric Exhibit B $3,900,000.00 | C6: CHICAGO DEPARTMENT OF TRANSPORTATION | D6: 1 | E6: 3900000 | F6: 20175951 | G6: 0.37918095 | H6: E. ROA - (Recommendation of Award) | I6: Claimed awarded - UNVERIFIED
A7: 3 | B7: Transfered from APRF No. 511278. Regular and emergency bus services at O'Hare Airport for January through March 2026 | C7: CHICAGO DEPARTMENT OF AVIATION | D7: 1 | E7: 3276126.9 | F7: 23452078 | G7: 0.44075153 | H7: F. SC - (Signature Cycle) | I7: Still open
A8: 4 | B8: Liquid Aluminum Sulfate (Iron Free) | C8: DEPARTMENT OF WATER MANAGEMENT | D8: 7 | E8: 3248945.8 | F8: 26701024 | G8: 0.50181127 | H8: A. Specification Development Phase | I8: Still open
A9: 5 | B9: Transfered from APRF No. 513665. Requesting a Direct Voucher - Exhibit B for O'Hare due to expired contract. Elevators,1-MOD/Final 7/27/26 nt | C9: CHICAGO DEPARTMENT OF AVIATION | D9: 3 | E9: 2596967.8 | F9: 29297991 | G9: 0.55061792 | H9: D. Solicitation Response Under Evaluation | I9: Still open
A10: 6 | B10: PURCHASE OF BLACK AND BLUE MOBILE CARTS | C10: DEPARTMENT OF STREETS AND SANITATION | D10: 4 | E10: 2406381.5 | F10: 31704373 | G10: 0.59584276 | H10: C. Solicitation or Bidding Phase | I10: Still open
A11: 7 | B11: Street and Parkway Restoration Central North Region | C11: DEPARTMENT OF WATER MANAGEMENT | D11: 2 | E11: 1902848.1 | F11: 33607221 | G11: 0.63160433 | H11: H. One Time Purchase | I11: Claimed awarded - UNVERIFIED
A12: 8 | B12: FFIB Industrial Fence $578,668.60 | C12: CHICAGO FIRE DEPARTMENT | D12: 22 | E12: 1061040.1 | F12: 34668261 | G12: 0.65154521 | H12: B. City Law Review | I12: Still open
A13: 9 | B13: Street and Parkway Restoration North Region | C13: DEPARTMENT OF WATER MANAGEMENT | D13: 1 | E13: 938950.36 | F13: 35607211 | G13: 0.66919157 | H13: H. One Time Purchase | I13: Claimed awarded - UNVERIFIED
A14: 10 | B14: PROVIDE AN ELECTRICIANCUSTOMER, TROUBLESHOOTACCURPRESS AND BACK GAUGE FOROPERATION | C14: CHICAGO DEPARTMENT OF TRANSPORTATION | D14: 10 | E14: 891296.67 | F14: 36498508 | G14: 0.68594234 | H14: B. City Law Review | I14: Still open
A15: 11 | B15: There is currently no active contract for Integrated Pest Management. The vendor chose not to extend beyond the May 29, 2025 expiration date. 2FM subm | C15: DEPARTMENT OF FLEET AND FACILITY MANAGEMENT | D15: 21 | E15: 824511.78 | F15: 37323020 | G15: 0.70143797 | H15: A. Specification Development Phase | I15: Still open
A16: 12 | B16: Street and Parkway and Restoration Project No. 19-623 Central South Region | C16: DEPARTMENT OF WATER MANAGEMENT | D16: 1 | E16: 687712.68 | F16: 38010733 | G16: 0.71436265 | H16: H. One Time Purchase | I16: Claimed awarded - UNVERIFIED
... A69: 65 | B69: Landscape Services North & South LSD | C69: CHICAGO DEPARTMENT OF TRANSPORTATION | D69: 1 | E69: 76280.53 | F69: 51056420 | G69: 0.9595395 | H69: B. City Law Review | I69: Still open
A70: 66 | B70: Greater Illinois Title Company Invoices from Nov 2025 to Dec 2025 | C70: DEPARTMENT OF PLANNING AND DEVELOPMENT | D70: 4 | E70: 74125 | F70: 51130545 | G70: 0.96093258 | I70: Still open
A71: 67 | B71: 1 invoice for CDWG That was canceled by mistake after 2FM merged with IT and the PO invoice was cancel and was not paid. | C71: DEPARTMENT OF TECHNOLOGY AND INNOVATION | D71: 1 | E71: 69919.94 | F71: 51200465 | G71: 0.96224664 | H71: H. One Time Purchase | I71: Still open
A72: 68 | B72: Community Services, (Testing and Vaccine Services) December 2025 | C72: CHICAGO DEPARTMENT OF PUBLIC HEALTH | D72: 1 | E72: 69415.23 | F72: 51269880 | G72: 0.96355121 | H72: A. Specification Development Phase | I72: Still open
A73: 69 | B73: ELECTRICALPRODUCTS AND SUPPLIES | C73: CHICAGO DEPARTMENT OF TRANSPORTATION | D73: 1 | E73: 69314.85 | F73: 51339195 | G73: 0.96485389 | H73: B. City Law Review | I73: Still open
A74: 70 | B74: STUMP GRINDING | C74: DEPARTMENT OF STREETS AND SANITATION | D74: 2 | E74: 68173.46 | F74: 51407368 | G74: 0.96613512 | H74: D. Solicitation Response Under Evaluation | I74: Still open
A75: 71 | B75: EXHIBIT B - TALOGY PO 251333 INVOICES $67,689.70 | C75: DEPARTMENT OF HUMAN RESOURCES | D75: 1 | E75: 67689.7 | F75: 51475058 | G75: 0.96740726 | H75: A. Specification Development Phase | I75: Claimed awarded - UNVERIFIED
A76: 72 | B76: S&S Lead Dept. 2FM utilizes PO 92930 for the Purchase of Paint Products and Accessories. The contract expired on 3/7/25. S&S submitted a replaceme | C76: DEPARTMENT OF FLEET AND FACILITY MANAGEMENT | D76: 3 | E76: 67075.71 | F76: 51542134 | G76: 0.96866786 | H76: A. Specification Development Phase | I76: Still open
A77: 73 | B77: Chemical reagents and larvicideSurveillance fee | C77: CHICAGO DEPARTMENT OF PUBLIC HEALTH | D77: 1 | E77: 66126.92 | F77: 51608261 | G77: 0.96991063 | H77: H. One Time Purchase | I77: Still open
A78: 74 | B78: BOTTLED DRINKING WATER, DISTILLED WATER & WATER COOLER RENTALS | C78: CHICAGO DEPARTMENT OF TRANSPORTATION | D78: 27 | E78: 63682.14 | F78: 51671943 | G78: 0.97110746 | H78: A. Specification Development Phase | I78: Still open
A79: 75 | B79: eBicycle purchase for Parking Enforcement Aides | C79: DEPARTMENT OF FINANCE | D79: 1 | E79: 61200 | F79: 51733143 | G79: 0.97225763 | H79: H. One Time Purchase | I79: Still open
A80: 76 | B80: PRINTING EQUIPMENT | C80: DEPARTMENT OF LAW | D80: 1 | E80: 60771.56 | F80: 51793914 | G80: 0.97339976 | H80: C. Solicitation or Bidding Phase | I80: Still open
A81: 77 | B81: Community Testing, Infection Prevention | C81: CHICAGO DEPARTMENT OF PUBLIC HEALTH | D81: 2 | E81: 60732.8 | F81: 51854647 | G81: 0.97454115 | H81: A. Specification Development Phase | I81: Still open
A82: 78 | B82: Feb 2026 Waste Management Services at Midway. To pay Invoice # 55883 | C82: CHICAGO DEPARTMENT OF AVIATION | D82: 2 | E82: 58167.62 | F82: 51912815 | G82: 0.97563434 | H82: A. Specification Development Phase | I82: Still open
... A131: 127 | B131: TB/JM/INVOICE #3931/$4000.00 | C131: DEPARTMENT OF FLEET AND FACILITY MANAGEMENT | D131: 2 | E131: 8000 | F131: 53117002 | G131: 0.99826548 | H131: A. Specification Development Phase | I131: Still open
A132: 128 | B132: CoStar Aug 2026 Invoice | C132: DEPARTMENT OF PLANNING AND DEVELOPMENT | D132: 2 | E132: 7906.6 | F132: 53124909 | G132: 0.99841407 | I132: Still open
A133: 129 | B133: Specialized supplies for preservation project of City Council archival materials. | C133: OFFICE OF CITY CLERK | D133: 1 | E133: 7396.57 | F133: 53132305 | G133: 0.99855308 | H133: H. One Time Purchase | I133: Still open
A134: 130 | B134: #2 Invoices $7,082.00 Requesting a Direct Voucher - Exhibit B for Ohare to due VLI. A VLI extension has been requested. | C134: CHICAGO DEPARTMENT OF AVIATION | D134: 1 | E134: 7082 | F134: 53139387 | G134: 0.99868618 | H134: D. Solicitation Response Under Evaluation | I134: Still open
A135: 131 | B135: Sewer Construction | C135: DEPARTMENT OF WATER MANAGEMENT | D135: 1 | E135: 6839.9 | F135: 53146227 | G135: 0.99881473 | H135: H. One Time Purchase | I135: Still open
A136: 132 | B136: TB/GR/INV #5072349294/$6015.80 | C136: DEPARTMENT OF FLEET AND FACILITY MANAGEMENT | D136: 1 | E136: 6015.8 | F136: 53152243 | G136: 0.99892779 | H136: A. Specification Development Phase | I136: Still open
A137: 133 | B137: Canon Copier Services Contract in VLI process | C137: CHICAGO ANIMAL CARE AND CONTROL | D137: 1 | E137: 5595.97 | F137: 53157839 | G137: 0.99903295 | H137: A. Specification Development Phase | I137: Still open
A138: 134 | B138: Republic Service Inv# 0710-005914497 | C138: CHICAGO POLICE DEPARTMENT | D138: 1 | E138: 4891.34 | F138: 53162730 | G138: 0.99912488 | H138: A. Specification Development Phase | I138: Still open
A139: 135 | B139: All In One Desktops | C139: CHICAGO DEPARTMENT OF PUBLIC HEALTH | D139: 1 | E139: 4815 | F139: 53167545 | G139: 0.99921537 | H139: H. One Time Purchase | I139: Claimed awarded - UNVERIFIED
A140: 136 | B140: A VLI was submitted to DPS in October 2024 under Rx 623996. We held invoices for the past five months in anticipation of the VLI approval, in an effor | C140: DEPARTMENT OF FLEET AND FACILITY MANAGEMENT | D140: 1 | E140: 4492.25 | F140: 53172037 | G140: 0.9992998 | H140: F. SC - (Signature Cycle) | I140: Still open
A141: 137 | B141: LKP Legislative services | C141: OFFICE OF THE MAYOR | D141: 1 | E141: 4000 | F141: 53176037 | G141: 0.99937497 | H141: H. One Time Purchase | I141: Still open
A142: 138 | B142: State Required Safety Lane Inspections for Public Safety Vehicles | C142: CHICAGO FIRE DEPARTMENT | D142: 6 | E142: 3783 | F142: 53179820 | G142: 0.99944607 | H142: A. Specification Development Phase | I142: Still open
A143: 139 | B143: TB/GR/2 INVOICES/$2999.00 | C143: DEPARTMENT OF FLEET AND FACILITY MANAGEMENT | D143: 2 | E143: 3726.43 | F143: 53183547 | G143: 0.9995161 | H143: B. City Law Review | I143: Still open
A144: 140 | B144: Hastings 1033282 B JS/ JG/ Invoice Number: O38604D102-B/ $3,451.50/ January / Exhaust System Maint Pt. 2 | C144: DEPARTMENT OF FLEET AND FACILITY MANAGEMENT | D144: 1 | E144: 3451.5 | F144: 53186998 | G144: 0.99958097 | H144: A. Specification Development Phase | I144: Claimed awarded - UNVERIFIED
A145: 141 | B145: FRANK COONEY, INV# 7005, INVOICE DATE 2/18/26, AMOUNT $2,893.75 | C145: DEPARTMENT OF HUMAN RESOURCES | D145: 1 | E145: 2893.75 | F145: 53189892 | G145: 0.99963535 | H145: H. One Time Purchase | I145: Claimed awarded - UNVERIFIED
A146: 142 | B146: Eusebio Molina Invoice for 10/23/2025 | C146: DEPARTMENT OF PLANNING AND DEVELOPMENT | D146: 1 | E146: 2100 | F146: 53191992 | G146: 0.99967482 | I146: Still open
A147: 143 | B147: medical pharmaceuticals Wood Dale Pharmacy - Apr 2026 | C147: CHICAGO ANIMAL CARE AND CONTROL | D147: 1 | E147: 2013.4 | F147: 53194006 | G147: 0.99971266 | H147: B. City Law Review | I147: Still open
A148: 144 | B148: WB/JR/INVOICE #9026432648/$1830.40 | C148: DEPARTMENT OF FLEET AND FACILITY MANAGEMENT | D148: 1 | E148: 1830.4 | F148: 53195836 | G148: 0.99974706 | H148: A. Specification Development Phase | I148: Still open
A149: 145 | B149: QUOTE#0578146 | C149: CHICAGO FIRE DEPARTMENT | D149: 1 | E149: 1735 | F149: 53197571 | G149: 0.99977967 | H149: A. Specification Development Phase | I149: Still open
A150: 146 | B150: INV#204824 | C150: CHICAGO FIRE DEPARTMENT | D150: 2 | E150: 1521 | F150: 53199092 | G150: 0.99980825 | H150: H. One Time Purchase | I150: Still open
A151: 147 | B151: WEB HOSTING, PRINTING AND MAIL MANAGEMENT SERVICES FOR CITY BILLINGS; DOB, WATER, & SEWER | C151: DEPARTMENT OF BUILDINGS | D151: 2 | E151: 1161.8 | F151: 53200254 | G151: 0.99983009 | H151: F. SC - (Signature Cycle) | I151: Still open
A152: 148 | B152: CONTRACT CURRENTLY WITH DPS FOR APPROVAL | C152: CHICAGO ANIMAL CARE AND CONTROL | D152: 2 | E152: 1013.42 | F152: 53201267 | G152: 0.99984913 | H152: B. City Law Review | I152: Still open
A153: 149 | B153: SCALES CERTIFICATION | C153: DEPARTMENT OF BUSINESS AFFAIRS AND CONSUMER PROTECTION | D153: 1 | E153: 980 | F153: 53202247 | G153: 0.99986755 | H153: H. One Time Purchase | I153: Still open
A154: 150 | B154: M02o5nthly Hosting Fee | C154: CHICAGO DEPARTMENT OF PUBLIC HEALTH | D154: 1 | E154: 833 | F154: 53203080 | G154: 0.99988321 | H154: B. City Law Review | I154: Still open
A155: 151 | B155: TB/DC/INV#68384/$825.00 | C155: DEPARTMENT OF FLEET AND FACILITY MANAGEMENT | D155: 1 | E155: 825 | F155: 53203905 | G155: 0.99989871 | H155: B. City Law Review | I155: Still open
A156: 152 | B156: de-binding services for City Council archival preservation project. | C156: OFFICE OF CITY CLERK | D156: 1 | E156: 825 | F156: 53204730 | G156: 0.99991422 | H156: H. One Time Purchase | I156: Still open
A157: 153 | B157: Orkin - pest control treatment at satellite office | C157: OFFICE OF CITY CLERK | D157: 1 | E157: 800 | F157: 53205530 | G157: 0.99992925 | H157: H. One Time Purchase | I157: Still open
A158: 154 | B158: Replace 2-12V Batteries for Core point Scientific Ric | C158: CHICAGO DEPARTMENT OF PUBLIC HEALTH | D158: 1 | E158: 787.58 | F158: 53206318 | G158: 0.99994405 | H158: H. One Time Purchase | I158: Still open
... A163: 159 | B163: ENVIRONMENTAL SERVICES | C163: CHICAGO DEPARTMENT OF PUBLIC HEALTH | D163: 1 | E163: 370.7 | F163: 53208538 | G163: 0.99998579 | H163: G. Not Applicable (Office Depot use Only) | I163: Still open
A164: 160 | B164: Parchment Paper for Resolutions | C164: OFFICE OF CITY CLERK | D164: 2 | E164: 335.35 | F164: 53208874 | G164: 0.99999209 | I164: Still open
A165: 161 | B165: Accurate Document Destruction (ADD) - Document Shredding Services Four (4) Cabinets DOS: 01/21/2026 Invoice.1592910T095 (Final Invoice) | C165: DEPARTMENT OF FINANCE | D165: 1 | E165: 276 | F165: 53209150 | G165: 0.99999727 | H165: H. One Time Purchase | I165: Still open
A166: 162 | B166: Technical support for software upgrade related to business license issuance | C166: OFFICE OF CITY CLERK | D166: 1 | E166: 145 | F166: 53209295 | G166: 1 | H166: H. One Time Purchase | I166: Still open
A167: 163 | B167: RAE Products 708377 A JS/ PM/ INVOICE # 204502/ $46,777.11/ | C167: DEPARTMENT OF FLEET AND FACILITY MANAGEMENT | D167: 1 | E167: 0 | F167: 53209295 | G167: 1 | H167: A. Specification Development Phase | I167: Still open
A168: 164 | B168: SVC ORDE#W00980681, W00980669 & W00980680 | C168: OFFICE OF EMERGENCY MANAGEMENT AND COMMUNICATIONS | D168: 1 | E168: 0 | F168: 53209295 | G168: 1 | H168: H. One Time Purchase | I168: Still open
A169: 165 | B169: Elizabeth Hernandez Order | C169: DEPARTMENT OF FLEET AND FACILITY MANAGEMENT | D169: 1 | E169: 0 | F169: 53209295 | G169: 1 | I169: Still open
A170: 166 | B170: LIFT TRUCKS, SCISSOR LIFTS AND PALLET JACKS- GROUPS: A, B, C, D, E & F | C170: DEPARTMENT OF FLEET AND FACILITY MANAGEMENT | D170: 1 | E170: 0 | F170: 53209295 | G170: 1 | I170: Still open
A171: 167 | B171: Vehicle boot repairs | C171: DEPARTMENT OF FINANCE | D171: 1 | E171: 0 | F171: 53209295 | G171: 1 | H171: H. One Time Purchase | I171: Still open

Sheet Pipeline Forecast
A1: PIPELINE FORECAST - WHAT CONVERTS NEXT
A2: Procurement Phase shows how far each Exhibit B requisition has progressed toward a contract. This turns a backward-looking scorecard into a forecast.
A4: Procurement Phase | B4: Expected Conversion Horizon | C4: Sourcing Efforts | D4: Requisitions | E4: Exhibit B Spend | F4: Share of Spend
A5: (not stated) | B5: unknown | C5: 6 | D5: 11 | E5: 84466.95 | F5: 0.0015799617
A6: A. Specification Development Phase | B6: 12+ months | C6: 71 | D6: 357 | E6: 23024247 | F6: 0.43067055
A7: B. City Law Review | B7: 6-12 months | C7: 42 | D7: 182 | E7: 8176786.7 | F7: 0.15294751
A8: C. Solicitation or Bidding Phase | B8: 3-6 months | C8: 12 | D8: 33 | E8: 2991599.2 | F8: 0.055958124
A9: D. Solicitation Response Under Evaluation | B9: 3-6 months | C9: 16 | D9: 30 | E9: 3699094.1 | F9: 0.069191877
A10: E. ROA - (Recommendation of Award) | B10: 0-3 months - imminent | C10: 5 | D10: 12 | E10: 5044003.9 | F10: 0.094348532
A11: F. SC - (Signature Cycle) | B11: 0-3 months - imminent | C11: 9 | D11: 13 | E11: 3543380.8 | F11: 0.066279246
A12: G. Not Applicable (Office Depot use Only) | B12: n/a - not applicable | C12: 5 | D12: 7 | E12: 555173.71 | F12: 0.010384573
A13: H. One Time Purchase | B13: n/a - one-time purchase | C13: 56 | D13: 85 | E13: 6342640 | F13: 0.11863963
A14: TOTAL | E14: =SUM(E5:E13) | F14: =SUM(F5:F13)
A16: NEAR-TERM HEADLINE: 25 requisitions worth $8,587,385 are in Recommendation of Award or Signature Cycle - one administrative step from a contract. Expect these to leave Exhibit B within 60-90 days.

Sheet Reverse Leakage
A1: REVERSE LEAKAGE - EXHIBIT B FILED AFTER THE CONTRACT EXISTED
A2: These requisitions were processed as contract exceptions AFTER an award covering that scope had already landed. The spend should have ridden the contract.
A4: Exhibit B Req# | B4: Exhibit B Date | C4: Department | D4: Description | E4: Spend That Should Have Ridden Contract | F4: Contract Award Date | G4: Awarded Vendor | H4: Awarded Contract ID | I4: Days After Award
A5: 744483 | B5: 46241 | C5: DEPARTMENT OF TECHNOLOGY AND INNOVATION | D5: 1- 2025 unpaid DLT invoice for Oracle Active Data Guard Processor. This invoice was received after the Finance cutoff re | E5: 48673.35 | F5: 46073 | G5: DLT SOLUTIONS LLC | H5: 387728 | I5: 168
A6: 737833 | B6: 46203 | C6: DEPARTMENT OF FLEET AND FACILITY MANAGEMENT | D6: Helicopter Inc. 10633647 A JS/ BJ/ 2-Invoices/ $18,497.54/ PD911Q/ WO 2626555/ ASR/50 HR inspection due and 150 hr engi | E6: 18497.54 | F6: 46203 | G6: Helicopters, Inc. | H6: 386844 | I6: 0
A7: 742855 | B7: 46231 | C7: DEPARTMENT OF FAMILY AND SUPPORT SERVICES | D7: Exhibit B_2 8160 | E7: 8160 | F7: 46203 | G7: Service Sanitation Inc. | H7: 381051 | I7: 28
A8: 742832 | B8: 46238 | C8: DEPARTMENT OF FAMILY AND SUPPORT SERVICES | D8: Exhibit B_ 8160 | E8: 8160 | F8: 46203 | G8: Service Sanitation Inc. | H8: 381051 | I8: 35
A9: 742887 | B9: 46231 | C9: DEPARTMENT OF FAMILY AND SUPPORT SERVICES | D9: Exhibit B_3_7644 | E9: 7644 | F9: 46203 | G9: Service Sanitation Inc. | H9: 381051 | I9: 28
A10: 746639 | B10: 46253.939 | C10: OFFICE OF THE MAYOR | D10: LKP Legislative services | E10: 4000 | F10: 46024 | G10: LKP CONSULTING LLC | H10: 386406 | I10: 229
A11: 734820 | B11: 46182 | C11: CHICAGO DEPARTMENT OF AVIATION | D11: Invoice# SS109523 Sherwin Industries FAA Part 139 Regulatory Compliance. Calibration of AFM2 (8 units) and labor for | E11: 3916 | F11: 46106 | G11: Halliday Technologies | H11: 375509 | I11: 76
A12: 745303 | B12: 46246 | C12: CHICAGO DEPARTMENT OF PUBLIC HEALTH | D12: OES:Odysseus Licensing FeeAnnual Licensing and Hosting Fee: June 2026 | E12: 833 | F12: 46220 | G12: INTEGRATED SOLUTIONS CONSULTING CORPORATION | H12: 386925 | I12: 26

Sheet Data Quality Findings
A1: DATA QUALITY FINDINGS
A2: Issues in the source data that limit measurement - and that are fixable at the point of entry.
A4: Finding | B4: Detail | C4: Impact on Measurement | D4: Recommended Fix
A5: 'Contract Number Awarded' is largely unusable | B5: 136 of 221 populated values are not contract numbers - they include 'TBD', 'na', '0', 'NO', 'yes', 'Pending', 'UNKNOWN', 'N?A' and 'None yet'. | C5: Cannot verify an award from this field alone | D5: Make it a validated numeric field, required only when 'Contract Awarded?' = Yes
A6: Claimed contract numbers do not reconcile | B6: 25 distinct numbers were supplied on rows claiming an award. Only 2 appear anywhere in the awarded contract file. | C6: The award claim cannot be substantiated for most rows | D6: Validate the entry against the contract master at the point of entry
A7: 'Requisition# for New Contract/Mod' is free text | B7: 91 of 654 values need parsing - 'RX 596048', 'RX676831- SPEC 1197406C', concatenated '710856710875', 'Target Market 710856, Non-Target Market 710875', 'na'. | C7: Automated tracking requires a cleanup pass every time | D7: Split into a numeric requisition field plus a free-text note field
A8: Awarded contract file has no requisition on every row | B8: 14 of 100 awarded contracts carry no REQ number, and 0 carry no SPEC. | C8: Those awards cannot be traced back to the Exhibit B that preceded them | D8: Require the originating requisition on every award record
A9: No shared key between the two systems | B9: Exhibit B and the award file share no reliable common identifier; linkage depends on requisition numbers appearing in a free-text field. | C9: Conversion cannot be measured automatically today | D9: Carry the Exhibit B requisition number forward onto the resulting award record

Sheet Methodology & Limits
A1: METHODOLOGY, DEFINITIONS AND LIMITATIONS
A2: Read this before quoting any number in this workbook.
B4: WHAT THIS ANALYSIS ANSWERS
B5: Question | C5: Did non-contract ('maverick') Exhibit B spend move onto a competitively awarded contract during the period?
B6: Two gates | C6: Gate 1 - did the spend exit Exhibit B onto an awarded contract? Gate 2 - was that award competitive (Bid/RFQ/RFP)? Exiting Exhibit B into a sole-source or emergency award clears the exception report but is not the procurement-correct outcome.
B8: UNIT OF ANALYSIS
B9: Sourcing effort | C9: Requisitions are rolled up to the pending new-contract requisition (RX). 730 Exhibit B requisitions represent only 175 distinct sourcing efforts. One effort absorbs 49 requisitions and $16,275,951. Counting requisitions overstates the number of problems and understates their size.
B11: EVIDENCE TIERS
B12: Tier A - Confirmed | C12: Hard ID link: the Exhibit B new-contract requisition equals an awarded REQ, or the reported contract number equals an awarded PO/CONTRACT_ID.
B13: Tier B - Confirmed | C13: Same vendor plus commodity-token overlap of 10% or more between the Exhibit B description and the award description.
B14: Tier C - Suggestive | C14: Same vendor only, no commodity overlap. NOT counted as a conversion.
B15: Tier D - Weak | C15: Description similarity of 30% or more with no vendor or ID link. NOT counted as a conversion.
B16: Tier E - None | C16: No linkage found in the awarded contract file.
B17: Timing gate | C17: A Tier A or B match counts as a conversion only if the award date is AFTER the Exhibit B date. A match with an earlier award date is reverse leakage, not a conversion.
B18: Headline basis | C18: The headline conversion figure uses Tier A and B only. Tiers C and D are disclosed separately and are never added to the headline.
B20: DENOMINATOR
B21: Expected to convert | C21: 'Request for New Contract/Mod' = Yes, excluding justifications 3. One Time Purchase, 4. Invoice Reconciliation, 6. Bid Protest - these are not intended to result in a contract. 476 requisitions ($40,335,240) meet this test.
B23: LIMITATIONS - READ BEFORE CITING
B24: Award file is a fixed list | C24: The awarded contract file contains 100 contracts. If it is not the complete population of awards for the period, an Exhibit B effort could have been awarded on a contract absent from this file. 'No verified conversion' therefore means 'not evidenced in the supplied award data' - it does not prove no award occurred.
B25: No shared key | C25: The two systems share no reliable common identifier. Linkage depends on requisition numbers appearing inside a free-text field, so some genuine conversions are likely unmatched. The verified figure is a floor, not a ceiling.
B26: Self-reported fields excluded | C26: 'Contract Awarded?' and 'Contract Number Awarded' are department self-reports and are analysed as a claim to be tested, never used as evidence of conversion.
B27: Spend basis | C27: Requisition Amount as submitted. Approved and denied rows are both retained in the population and flagged; denied rows never count as converted.
B28: Period | C28: January 5, 2026 to August 20, 2026. Both tabs cover the same window, so an Exhibit B request late in the period has had little time to reach award - conversion for recent months is understated by construction.
B30: SOURCE DATA
B31: Exhibit B tab | C31: 730 requisitions, $53,461,392.14
B32: Awarded contracts tab | C32: 100 contracts, $2,591,929,537.52 total award value (full award book, not only Exhibit B conversions)
B33: Competitive definition | C33: PROCUREMENT_TYPE in ['BID', 'RFP', 'RFQ']. 53 of 100 awards qualify.

Sheet EB Detail
A1: Requisition Number | B1: Exhibit B Date | C1: Department | D1: Vendor | E1: Description | F1: Amount | G1: Justification | H1: Procurement Phase | I1: Approved or Denied | J1: New Contract Requested | K1: Self-Reported Awarded | L1: Contract # Claimed | M1: Sourcing Key | N1: Evidence Tier | O1: Match Basis | P1: Awarded Contract ID | Q1: Awarded Vendor | R1: Award Date | S1: Procurement Type | T1: Competitive | U1: Converted | V1: Reverse Leak | W1: Expected to Convert
A2: 737798 | B2: 46203 | C2: DEPARTMENT OF WATER MANAGEMENT | D2: PAN-OCEANIC ENGINEERING CO INC | E2: Sewer Construction | F2: 121426.74 | G2: 1. Pending New Contract - Original Contract Expired. New Contract in Process | H2: H. One Time Purchase | I2: APPROVED | J2: Yes | K2: Yes | L2: 297413 | M2: VDPAN OCEANIC ENGINEERING | N2: E | O2: No linkage found in awarded contract file | T2: No | U2: No | V2: No | W2: Yes
A3: 734966 | B3: 46182 | C3: DEPARTMENT OF WATER MANAGEMENT | D3: SEVEN D CONSTRUCTION COMPANY | E3: Street and Parkway Repair Project NO. 19-625 North Region | F3: 143357.36 | G3: 1. Pending New Contract - Original Contract Expired. New Contract in Process | H3: H. One Time Purchase | I3: APPROVED | J3: Yes | K3: Yes | L3: 272860 | M3: RX492769 | N3: C | O3: Vendor name match only (similarity 0.00) | P3: 383513 | Q3: SEVEN D CONSTRUCTION COMPANY | R3: 46107 | S3: BID | T3: Yes | U3: No | V3: No | W3: Yes
A4: 741608 | B4: 46223 | C4: DEPARTMENT OF WATER MANAGEMENT | D4: CHARLES EQUIPMENT ENERGY SYSTEMS LLC | E4: Perform 2025 annual planned maintenance on one Caterpillar chlorine emergency power generator and five MTU main plant power emergency generators | F4: 33822.1 | G4: 1. Pending New Contract - Original Contract Expired. New Contract in Process | H4: H. One Time Purchase | I4: APPROVED | J4: Yes | K4: No | M4: RX622326 | N4: E | O4: No linkage found in awarded contract file | T4: No | U4: No | V4: No | W4: Yes
A5: 742464 | B5: 46226 | C5: DEPARTMENT OF FLEET AND FACILITY MANAGEMENT | D5: JACOB PRESS' SONS INC | E5: WB/MM/INVOICE#598412/$1221.66 | F5: 1221.66 | G5: 1. Pending New Contract - Original Contract Expired. New Contract in Process | H5: B. City Law Review | I5: DENIED | J5: Yes | K5: No | M5: RX590958 | N5: E | O5: No linkage found in awarded contract file | T5: No | U5: No | V5: No | W5: Yes
A6: 726600 | B6: 46146 | C6: DEPARTMENT OF BUSINESS AFFAIRS AND CONSUMER PROTECTION | D6: WALZ SCALES CO. | E6: SCALES CERTIFICATION | F6: 980 | G6: 3. One Time Purchase | H6: H. One Time Purchase | I6: APPROVED | J6: Yes | K6: No | M6: VDWALZ SCALES | N6: E | O6: No linkage found in awarded contract file | T6: No | U6: No | V6: No | W6: No
A7: 742345 | B7: 46226 | C7: CHICAGO FIRE DEPARTMENT | D7: ACORN GARAGE INC | E7: INV#204824 | F7: 273 | G7: 1. Pending New Contract - Original Contract Expired. New Contract in Process | H7: H. One Time Purchase | I7: DENIED | J7: No | K7: No | M7: RX680611 | N7: E | O7: No linkage found in awarded contract file | T7: No | U7: No | V7: No | W7: No
A8: 739577 | B8: 46210 | C8: CHICAGO FIRE DEPARTMENT | D8: TELEFLEX LLC | E8: QUOTE#0578146 | F8: 1735 | G8: 1. Pending New Contract - Original Contract Expired. New Contract in Process | H8: A. Specification Development Phase | I8: DENIED | J8: Yes | K8: No | M8: RX695898 | N8: E | O8: No linkage found in awarded contract file | T8: No | U8: No | V8: No | W8: Yes
A9: 707111 | B9: 46027 | C9: DEPARTMENT OF BUILDINGS | D9: A & D PROPERTY SERVICES, INC. | E9: BOARD UP SERVICES | F9: 38700 | G9: 1. Pending New Contract - Original Contract Expired. New Contract in Process | H9: A. Specification Development Phase | I9: APPROVED | J9: Yes | K9: No | L9: 32040 | M9: RX659422 | N9: E | O9: No linkage found in awarded contract file | T9: No | U9: No | V9: No | W9: Yes
A10: 718143 | B10: 46087 | C10: DEPARTMENT OF BUILDINGS | D10: A & D PROPERTY SERVICES, INC. | E10: BOARD UP SERVICES | F10: 43650 | G10: 1. Pending New Contract - Original Contract Expired. New Contract in Process | H10: B. City Law Review | I10: APPROVED | J10: Yes | K10: No | L10: 32040 | M10: RX659422 | N10: E | O10: No linkage found in awarded contract file | T10: No | U10: No | V10: No | W10: Yes
A11: 716026 | B11: 46078 | C11: OFFICE OF THE MAYOR | D11: Berlin Rosen, LLC | E11: Berlin Rosen Public relations Nov/Dec 2025 | F11: 9975.75 | G11: 3. One Time Purchase | H11: H. One Time Purchase | I11: APPROVED | J11: No | K11: No | L11: none | M11: VDBERLIN ROSEN | N11: E | O11: No linkage found in awarded contract file | T11: No | U11: No | V11: No | W11: No
A12: 745000 | B12: 46245 | C12: DEPARTMENT OF FLEET AND FACILITY MANAGEMENT | D12: P. R. STREICH & SONS | E12: KB/MM/ INV#56736/ $693.39 | F12: 693.39 | G12: 1. Pending New Contract - Original Contract Expired. New Contract in Process | H12: B. City Law Review | I12: APPROVED | J12: Yes | K12: No | L12: TBD | M12: RX679901 | N12: E | O12: No linkage found in awarded contract file | T12: No | U12: No | V12: No | W12: Yes
A13: 708310 | B13: 46035 | C13: CHICAGO DEPARTMENT OF PUBLIC HEALTH | D13: CIS Support, Inc. | E13: CIS Maintenance/Support-December | F13: 5500 | G13: 1. Pending New Contract - Original Contract Expired. New Contract in Process | H13: H. One Time Purchase | I13: APPROVED | J13: Yes | K13: No | M13: VDCIS SUPPORT | N13: E | O13: No linkage found in awarded contract file | T13: No | U13: No | V13: No | W13: Yes
A14: 707519 | B14: 46031 | C14: DEPARTMENT OF WATER MANAGEMENT | D14: USALCO | E14: Liquid Aluminum Sulfate (Iron Free) | F14: 663663.84 | G14: 1. Pending New Contract - Original Contract Expired. New Contract in Process | H14: A. Specification Development Phase | I14: APPROVED | J14: Yes | K14: No | M14: RX661351 | N14: E | O14: No linkage found in awarded contract file | T14: No | U14: No | V14: No | W14: Yes
A15: 737495 | B15: 46197 | C15: CHICAGO FIRE DEPARTMENT | D15: INDUSTRIAL FENCE INC. | E15: FFIB Industrial Fence $578,668.60 | F15: 578668.6 | G15: 1. Pending New Contract - Original Contract Expired. New Contract in Process | H15: B. City Law Review | I15: DENIED | J15: No | K15: No | M15: RX596048 | N15: E | O15: No linkage found in awarded contract file | T15: No | U15: No | V15: No | W15: No
A16: 740144 | B16: 46220 | C16: DEPARTMENT OF FAMILY AND SUPPORT SERVICES | D16: DIRECT FITNESS SOLUTIONS, LLC | E16: Aps 82_Fitness Equipment Maintenance Project | F16: 0 | G16: 1. Pending New Contract - Original Contract Expired. New Contract in Process | H16: A. Specification Development Phase | I16: APPROVED | J16: No | K16: No | M16: RX609670 | N16: E | O16: No linkage found in awarded contract file | T16: No | U16: No | V16: No | W16: No
A17: 709818 | B17: 46044 | C17: DEPARTMENT OF FLEET AND FACILITY MANAGEMENT | D17: RUNNION EQUIPMENT CO | E17: We currently do not have a contract in place due to City Utility (PO # 17836) no longer performing this work for us. These aerial bucket trucks are used by CDOT (street light and traffic signal installation and repair), Streets & Sanitation | F17: 6681 | G17: 1. Pending New Contract - Original Contract Expired. New Contract in Process | H17: B. City Law Review | I17: APPROVED | J17: Yes | K17: No | M17: RX590958 | N17: E | O17: No linkage found in awarded contract file | T17: No | U17: No | V17: No | W17: Yes
A18: 728640 | B18: 46146 | C18: DEPARTMENT OF FLEET AND FACILITY MANAGEMENT | D18: RUNNION EQUIPMENT CO | E18: We currently do not have a contract in place due to City Utility (PO # 17836) no longer performing this work for us. These aerial bucket trucks are used by CDOT (street light and traffic signal installation and repair), Streets & Sanitation | F18: 9754.65 | G18: 1. Pending New Contract - Original Contract Expired. New Contract in Process | H18: B. City Law Review | I18: APPROVED | J18: Yes | K18: No | M18: RX590958 | N18: E | O18: No linkage found in awarded contract file | T18: No | U18: No | V18: No | W18: Yes
A19: 738075 | B19: 46203 | C19: DEPARTMENT OF FLEET AND FACILITY MANAGEMENT | D19: BELLA BAGNO INC | E19: Bella Bagno Inc is removing and installing carpet at the Bucktown/Wicker Park Branch Library. The labor services are outside of the contract prevue, and should be paid under Exhibit B. CDA has a new solicitation for purchase and installatio | F19: 147666.41 | G19: 1. Pending New Contract - Original Contract Expired. New Contract in Process | H19: D. Solicitation Response Under Evaluation | I19: APPROVED | J19: Yes | K19: Yes | M19: RX628102 | N19: E | O19: No linkage found in awarded contract file | T19: No | U19: No | V19: No | W19: Yes
A20: 728179 | B20: 46142 | C20: DEPARTMENT OF FLEET AND FACILITY MANAGEMENT | D20: P. R. STREICH & SONS | E20: There is curently no active contract with a vendor to repair and certify the shop floor equipment. Our previous vendor, Standard Industrial (PO 24519) did not want to extend their contract. Due to this 2FM found a local vendor PR Streich to | F20: 925 | G20: 1. Pending New Contract - Original Contract Expired. New Contract in Process | H20: B. City Law Review | I20: APPROVED | J20: Yes | K20: No | L20: TBD | M20: RX679901 | N20: E | O20: No linkage found in awarded contract file | T20: No | U20: No | V20: No | W20: Yes
A21: 721747 | B21: 46107 | C21: DEPARTMENT OF FLEET AND FACILITY MANAGEMENT | D21: Service Sanitation Inc. | E21: DCASE submitted a new contract request for RENTAL AND MAINTENANCE OF PORTABLE CHEMICAL TOILETS, SINKS, WASTE WATER BARRELS, PORTABLE WATERLESS HAND SANITIZER DISPENSERS, FRESH WATER TRAILER AND PORTABLE SHOWERS to DPS under RX 613315, Spec | F21: 247.5 | G21: 1. Pending New Contract - Original Contract Expired. New Contract in Process | H21: D. Solicitation Response Under Evaluation | I21: APPROVED | J21: Yes | K21: No | M21: RX700212 | N21: B | O21: Vendor match + commodity overlap (similarity 0.64) | P21: 381051 | Q21: Service Sanitation Inc. | R21: 46203 | S21: BID | T21: Yes | U21: Yes | V21: No | W21: Yes
A22: 737334 | B22: 46197 | C22: DEPARTMENT OF FLEET AND FACILITY MANAGEMENT | D22: ABM INDUSTRY GROUPS, LLC | E22: There was an active contract for Comprehensive Custodial Services for Zones 1, 2, and 4, which expire on February 13, 2026. 2FM previously submitted a modification request for a time extension and VLI under RX 680673; however, the request | F22: 266459.09 | G22: 1. Pending New Contract - Original Contract Expired. New Contract in Process | H22: A. Specification Development Phase | I22: APPROVED | J22: Yes | K22: No | M22: RX624331 | N22: E | O22: No linkage found in awarded contract file | T22: No | U22: No | V22: No | W22: Yes
A23: 740290 | B23: 46217 | C23: DEPARTMENT OF FLEET AND FACILITY MANAGEMENT | D23: ABM INDUSTRY GROUPS, LLC | E23: There was an active contract for Comprehensive Custodial Services for Zones 1, 2, and 4, which expire on February 13, 2026. 2FM previously submitted a modification request for a time extension and VLI under RX 680673; however, the reques | F23: 984580.81 | G23: 1. Pending New Contract - Original Contract Expired. New Contract in Process | H23: A. Specification Development Phase | I23: APPROVED | J23: Yes | K23: No | M23: RX624331 | N23: E | O23: No linkage found in awarded contract file | T23: No | U23: No | V23: No | W23: Yes
A24: 737251 | B24: 46197 | C24: DEPARTMENT OF FLEET AND FACILITY MANAGEMENT | D24: KING TRANSMISSION CO INC | E24: King Transmission had a contract (PO 34964) with the City that expired 4/19/24. 2FM submitted a TE Request that was rejected by DPS due to King's inability to comply with M/WBE requirements. King requested a waiver twice and was rejected bo | F24: 8590 | G24: 1. Pending New Contract - Original Contract Expired. New Contract in Process | H24: B. City Law Review | I24: APPROVED | J24: Yes | K24: No | M24: RX590958 | N24: E | O24: No linkage found in awarded contract file | T24: No | U24: No | V24: No | W24: Yes
A25: 722363 | B25: 46119 | C25: DEPARTMENT OF FLEET AND FACILITY MANAGEMENT | D25: ARLINGTON GLASS & MIRROR | E25: Arlington did not want to proceed with the contract extension unless they had their price increases. CDA put forth 3 price increases for 5% each. DPS would not approve all 3 price increases at 5%. They would give only 1 but at approx. 3%, | F25: 3058.86 | G25: 1. Pending New Contract - Original Contract Expired. New Contract in Process | H25: A. Specification Development Phase | I25: APPROVED | J25: Yes | K25: No | M25: RX647383 | N25: E | O25: No linkage found in awarded contract file | T25: No | U25: No | V25: No | W25: Yes
A26: 744391 | B26: 46241 | C26: DEPARTMENT OF FLEET AND FACILITY MANAGEMENT | D26: MURNANE PAPER COMPANY | E26: There is currently no active contract for this type of paper. The items being purchased are not part of the current Murnane contract. The Department of Fleet and Facility Management (2FM) previously advertised Specification 1288508, RX 579 | F26: 8624 | G26: 1. Pending New Contract - Original Contract Expired. New Contract in Process | H26: A. Specification Development Phase | I26: APPROVED | J26: No | K26: No | M26: RX600854 | N26: E | O26: No linkage found in awarded contract file | T26: No | U26: No | V26: No | W26: No
A27: 721742 | B27: 46107 | C27: DEPARTMENT OF FLEET AND FACILITY MANAGEMENT | D27: MURNANE PAPER COMPANY | E27: There is currently no active contract for this type of paper. The items being purchased are not part of the current Murnane contract. The Department of Fleet and Facility Management (2FM) previously advertised Specification 1288508, RX 579 | F27: 19759 | G27: 1. Pending New Contract - Original Contract Expired. New Contract in Process | H27: A. Specification Development Phase | I27: APPROVED | J27: No | K27: No | M27: RX600854 | N27: E | O27: No linkage found in awarded contract file | T27: No | U27: No | V27: No | W27: No
A28: 709915 | B28: 46048 | C28: DEPARTMENT OF FLEET AND FACILITY MANAGEMENT | D28: ABC Humane Wildlife Control & Prevention, Inc. | E28: There is currently no active contract for Integrated Pest Management. The vendor chose not to extend beyond the May 29, 2025 expiration date. 2FM submitted a replacement specification under RX 579113, Spec #1291433, which was advertised on | F28: 61600.38 | G28: 1. Pending New Contract - Original Contract Expired. New Contract in Process | H28: A. Specification Development Phase | I28: APPROVED | J28: No | K28: No | M28: RX682957 | N28: E | O28: No linkage found in awarded contract file | T28: No | U28: No | V28: No | W28: No
A29: 728515 | B29: 46146 | C29: DEPARTMENT OF FLEET AND FACILITY MANAGEMENT | D29: Helicopters, Inc. | E29: 2FM currently holds two helicopter maintenance contracts; however, the Bell 407 and 429 aircraft are not covered under either agreement due to a lack of certified personnel. To address this gap, 2FM submitted an Emergency Contract request f | F29: 89734.76 | G29: 1. Pending New Contract - Original Contract Expired. New Contract in Process | H29: B. City Law Review | I29: APPROVED | J29: Yes | K29: No | L29: TBD | M29: RX690671 | N29: A | O29: Requisition ID link: Exhibit B new-contract RX = awarded REQ | P29: 386844 | Q29: Helicopters, Inc. | R29: 46203 | S29: EMERGENCY | T29: No | U29: Yes | V29: No | W29: Yes
A30: 722397 | B30: 46126 | C30: DEPARTMENT OF FLEET AND FACILITY MANAGEMENT | D30: DAYSPRING PROFESSIONAL JANITOR | E30: There was an active contract for Comprehensive Custodial Services for Zones 1, 2, and 4, which expire on February 13, 2026. 2FM previously submitted a modification request for a time extension and vendor limit increase (VLI) under RX 680 | F30: 407334.07 | G30: 1. Pending New Contract - Original Contract Expired. New Contract in Process | H30: A. Specification Development Phase | I30: APPROVED | J30: Yes | K30: No | M30: RX624331 | N30: E | O30: No linkage found in awarded contract file | T30: No | U30: No | V30: No | W30: Yes
A31: 725748 | B31: 46136 | C31: DEPARTMENT OF FLEET AND FACILITY MANAGEMENT | D31: TOTAL FACILITY MAINTENANCE | E31: There was an active contract for Comprehensive Custodial Services which expired on February 15, 2026. 2FM previously submitted a modification request for a time extension and vendor limit increase (VLI) under RX 680779; however, the requ | F31: 161282.16 | G31: 1. Pending New Contract - Original Contract Expired. New Contract in Process | H31: B. City Law Review | I31: APPROVED | J31: Yes | K31: No | M31: RX624331 | N31: E | O31: No linkage found in awarded contract file | T31: No | U31: No | V31: No | W31: Yes
A32: 724629 | B32: 46133 | C32: DEPARTMENT OF FLEET AND FACILITY MANAGEMENT | D32: WISS, JANNEY, ELSTNER, & ASSOCIATES, INC. | E32: Current Spec 127930's Scope of services for this Exhibit B is outside of the current contract. Additional language was added to the new Specification for A/E, Spec#132104 Req.#607835, to address this scope gap in the future. Spec#132104 Req | F32: 8210.66 | G32: 1. Pending New Contract - Original Contract Expired. New Contract in Process | H32: H. One Time Purchase | I32: APPROVED | J32: Yes | K32: No | L32: 203199 | M32: RX607835 | N32: E | O32: No linkage found in awarded contract file | T32: No | U32: No | V32: No | W32: Yes
A33: 724038 | B33: 46129 | C33: DEPARTMENT OF WATER MANAGEMENT | D33: USALCO | E33: Liquid Aluminum Sulfate (Iron Free) | F33: 708176.6 | G33: 2. Pending Amendment/Modification - Line Item Addition / Vendor Limit Increase / Scope Change | H33: A. Specification Development Phase | I33: APPROVED | J33: Yes | K33: No | M33: RX661351 | N33: E | O33: No linkage found in awarded contract file | T33: No | U33: No | V33: No | W33: Yes
A34: 711297 | B34: 46052 | C34: CHICAGO ANIMAL CARE AND CONTROL | D34: LEGEND & WHITE ANIMAL HEALTH | E34: ANIMAL CARE AND CONTROL SUPPLIES | F34: 24988.24 | G34: 1. Pending New Contract - Original Contract Expired. New Contract in Process | H34: A. Specification Development Phase | I34: APPROVED | J34: No | K34: No | L34: NO | M34: VDLEGEND WHITE ANIMAL HEALTH | N34: E | O34: No linkage found in awarded contract file | T34: No | U34: No | V34: No | W34: No
A35: 728242 | B35: 46142 | C35: CHICAGO DEPARTMENT OF TRANSPORTATION | D35: BLUETRITON BRANDS INC | E35: BOTTLED DRINKING WATER, DISTILLED WATER & WATER COOLER RENTALS | F35: 170.86 | G35: 1. Pending New Contract - Original Contract Expired. New Contract in Process | H35: A. Specification Development Phase | I35: APPROVED | J35: No | K35: No | M35: RX676831 | N35: E | O35: No linkage found in awarded contract file | T35: No | U35: No | V35: No | W35: No
A36: 738378 | B36: 46203 | C36: DEPARTMENT OF STREETS AND SANITATION | D36: CASCADE ENGINEERING, INC | E36: PURCHASE OF BLACK AND BLUE MOBILE CARTS | F36: 580153.6 | G36: 1. Pending New Contract - Original Contract Expired. New Contract in Process | H36: C. Solicitation or Bidding Phase | I36: APPROVED | J36: Yes | K36: No | L36: 0 | M36: RX634792 | N36: E | O36: No linkage found in awarded contract file | T36: No | U36: No | V36: No | W36: Yes
A37: 738410 | B37: 46253 | C37: DEPARTMENT OF STREETS AND SANITATION | D37: CASCADE ENGINEERING, INC | E37: PURCHASE OF BLACK AND BLUE MOBILE CARTS | F37: 630234.8 | G37: 1. Pending New Contract - Original Contract Expired. New Contract in Process | H37: C. Solicitation or Bidding Phase | I37: DENIED | J37: Yes | K37: No | L37: 0 | M37: RX634792 | N37: E | O37: No linkage found in awarded contract file | T37: No | U37: No | V37: No | W37: Yes
A38: 707043 | B38: 46027 | C38: CHICAGO DEPARTMENT OF TRANSPORTATION | D38: A SAFE HAVEN FOUNDATION | E38: Landscape Maintenance Services | F38: 92090.14 | G38: 1. Pending New Contract - Original Contract Expired. New Contract in Process | H38: B. City Law Review | I38: APPROVED | J38: Yes | K38: No | L38: na | M38: RX596443 | N38: E | O38: No linkage found in awarded contract file | T38: No | U38: No | V38: No | W38: Yes
A39: 741283 | B39: 46220 | C39: CHICAGO DEPARTMENT OF TRANSPORTATION | D39: CHRISTY WEBBER LANDSCAPES | E39: Landscaping Services Regions 2 and 6 | F39: 17432.81 | G39: 1. Pending New Contract - Original Contract Expired. New Contract in Process | H39: B. City Law Review | I39: APPROVED | J39: Yes | K39: No | L39: na | M39: RX679137 | N39: E | O39: No linkage found in awarded contract file | T39: No | U39: No | V39: No | W39: Yes
A40: 708412 | B40: 46035 | C40: CHICAGO DEPARTMENT OF TRANSPORTATION | D40: LIZZETTE MEDINA & COMPANY | E40: LANDSCAPE SERVICES, REGIONS III & V | F40: 7331.24 | G40: 1. Pending New Contract - Original Contract Expired. New Contract in Process | H40: B. City Law Review | I40: APPROVED | J40: Yes | K40: No | L40: na | M40: RX652655 | N40: E | O40: No linkage found in awarded contract file | T40: No | U40: No | V40: No | W40: Yes
A41: 717524 | B41: 46085 | C41: OFFICE OF CITY CLERK | D41: VERITIV OPERATING COMPANY | E41: Parchment Paper for City Council Resolutions | F41: 335.35 | G41: 1. Pending New Contract - Original Contract Expired. New Contract in Process | H41: B. City Law Review | I41: APPROVED | J41: No | K41: No | L41: no | M41: RX600854 | N41: E | O41: No linkage found in awarded contract file | T41: No | U41: No | V41: No | W41: No
A42: 740376 | B42: 46217 | C42: CHICAGO POLICE DEPARTMENT | D42: REPUBLIC SERVICES INC | E42: Republic Services Inv# 005898442 | F42: 4878.77 | G42: 1. Pending New Contract - Original Contract Expired. New Contract in Process | H42: A. Specification Development Phase | I42: APPROVED | J42: Yes | K42: No | M42: RX669739 | N42: E | O42: No linkage found in awarded contract file | T42: No | U42: No | V42: No | W42: Yes
A43: 711716 | B43: 46052 | C43: CHICAGO DEPARTMENT OF PUBLIC HEALTH | D43: INTEGRATED SOLUTIONS CONSULTING CORPORATION | E43: M02o5nthly Hosting Fee | F43: 833 | G43: 1. Pending New Contract - Original Contract Expired. New Contract in Process | H43: B. City Law Review | I43: APPROVED | J43: Yes | K43: No | M43: VDINTEGRATED SOLUTIONS CONSULT | N43: C | O43: Vendor name match only (similarity 0.00) | P43: 386925 | Q43: INTEGRATED SOLUTIONS CONSULTING CORPORATION | R43: 46220 | S43: SOLE SOURCE | T43: No | U43: No | V43: No | W43: Yes
A44: 711218 | B44: 46052 | C44: OFFICE OF PUBLIC SAFETY ADMINISTRATION | D44: RAE PRODUCTS & CHEMICALS CORP. | E44: RAE Products Inv# 204193 | F44: 12233 | G44: 1. Pending New Contract - Original Contract Expired. New Contract in Process | H44: A. Specification Development Phase | I44: APPROVED | J44: No | K44: No | M44: VDRAE PRODUCTS CHEMICALS | N44: E | O44: No linkage found in awarded contract file | T44: No | U44: No | V44: No | W44: No
A45: 714540 | B45: 46077 | C45: CHICAGO DEPARTMENT OF AVIATION | D45: DTN, LLC | E45: DECEMBER 2025 INVOICE FOR O'HARE AIRPORT | F45: 3105 | G45: 5. User Dept. Decision - Elects to Purchase Smaller Goods or Services not Covered by Existing Contract | H45: D. Solicitation Response Under Evaluation | I45: APPROVED | J45: Yes | K45: No | M45: RX656425 | N45: E | O45: No linkage found in awarded contract file | T45: No | U45: No | V45: No | W45: Yes
A46: 720294 | B46: 46104 | C46: CHICAGO DEPARTMENT OF AVIATION | D46: DELAWARE CARS/T.R. HARMSEN CORP. J.V. | E46: Transfered from APRF No. 511278. Regular and emergency bus services at O'Hare Airport for January through March 2026 | F46: 3276126.9 | G46: 2. Pending Amendment/Modification - Line Item Addition / Vendor Limit Increase / Scope Change | H46: F. SC - (Signature Cycle) | I46: APPROVED | J46: Yes | K46: No | M46: RX686938 | N46: E | O46: No linkage found in awarded contract file | T46: No | U46: No | V46: No | W46: Yes
A47: 711733 | B47: 46052 | C47: OFFICE OF CITY CLERK | D47: SEBIS DIRECT | E47: Office of the City Clerk - Chicago Vehicle Stickers | F47: 32830.95 | G47: 1. Pending New Contract - Original Contract Expired. New Contract in Process | H47: A. Specification Development Phase | J47: No | K47: No | M47: VDSEBIS DIRECT | N47: E | O47: No linkage found in awarded contract file | T47: No | U47: No | V47: No | W47: No
A48: 708186 | B48: 46035 | C48: OFFICE OF CITY CLERK | D48: OMICRON TECHNOLOGY SOLUTIONS LLC | E48: Omicron CityKey Annual Licensing | F48: 158000 | G48: 1. Pending New Contract - Original Contract Expired. New Contract in Process | H48: B. City Law Review | J48: Yes | K48: No | M48: RX608757 | N48: E | O48: No linkage found in awarded contract file | T48: No | U48: No | V48: No | W48: Yes
A49: 720847 | B49: 46107 | C49: OFFICE OF CITY CLERK | D49: TAYLOR COMMUNICATIONS INC | E49: City Sticker Design Services | F49: 54 | G49: 1. Pending New Contract - Original Contract Expired. New Contract in Process | H49: A. Specification Development Phase | I49: APPROVED | J49: Yes | K49: No | M49: RX712876 | N49: E | O49: No linkage found in awarded contract file | T49: No | U49: No | V49: No | W49: Yes
A50: 740306 | B50: 46217 | C50: OFFICE OF CITY CLERK | D50: BAN-KOE SYSTEMS, INC | E50: Technical support for software upgrade related to business license issuance | F50: 145 | G50: 3. One Time Purchase | H50: H. One Time Purchase | I50: APPROVED | J50: No | K50: No | M50: VDBAN KOE SYSTEMS | N50: E | O50: No linkage found in awarded contract file | T50: No | U50: No | V50: No | W50: No
A51: 712884 | B51: 46084 | C51: OFFICE OF CITY CLERK | D51: SEBIS DIRECT | E51: Vehicle Stickers | F51: 0 | G51: 1. Pending New Contract - Original Contract Expired. New Contract in Process | H51: B. City Law Review | J51: No | K51: No | M51: VDSEBIS DIRECT | N51: E | O51: No linkage found in awarded contract file | T51: No | U51: No | V51: No | W51: No
A52: 712883 | B52: 46084 | C52: OFFICE OF CITY CLERK | D52: SEBIS DIRECT | E52: City Sticker Envelopes | F52: 0 | G52: 1. Pending New Contract - Original Contract Expired. New Contract in Process | H52: B. City Law Review | J52: No | K52: No | M52: VDSEBIS DIRECT | N52: E | O52: No linkage found in awarded contract file | T52: No | U52: No | V52: No | W52: No
A53: 746615 | B53: 46253 | C53: DEPARTMENT OF STREETS AND SANITATION | D53: CHICAGO UNITED INDUSTRIES, LTD | E53: TARP - SALT TARPING | F53: 327473.06 | G53: 1. Pending New Contract - Original Contract Expired. New Contract in Process | H53: A. Specification Development Phase | I53: APPROVED | J53: Yes | K53: No | M53: RX746444 | N53: E | O53: No linkage found in awarded contract file | T53: No | U53: No | V53: No | W53: Yes
A54: 746182 | B54: 46251 | C54: DEPARTMENT OF STREETS AND SANITATION | D54: BLUETRITON BRANDS INC | E54: WATER - DRINKING | F54: 1054.4 | G54: 1. Pending New Contract - Original Contract Expired. New Contract in Process | H54: A. Specification Development Phase | I54: APPROVED | J54: Yes | K54: No | M54: RX511569 | N54: E | O54: No linkage found in awarded contract file | T54: No | U54: No | V54: No | W54: Yes
A55: 715546 | B55: 46077 | C55: DEPARTMENT OF FLEET AND FACILITY MANAGEMENT | D55: CHRISTY WEBBER LANDSCAPES | E55: TB/AH/10 INVOICES/$85,350.30 | F55: 85350.3 | G55: 1. Pending New Contract - Original Contract Expired. New Contract in Process | H55: B. City Law Review | I55: APPROVED | J55: Yes | K55: No | M55: RX652655 | N55: E | O55: No linkage found in awarded contract file | T55: No | U55: No | V55: No | W55: Yes
A56: 709909 | B56: 46048 | C56: DEPARTMENT OF FLEET AND FACILITY MANAGEMENT | D56: A.M. BUS COMPANY, INC. | E56: TB/GC/INV #189156/$45,500.00 | F56: 45500 | G56: 3. One Time Purchase | H56: H. One Time Purchase | J56: No | K56: No | L56: 253967 | M56: RX624517 | N56: E | O56: No linkage found in awarded contract file | T56: No | U56: No | V56: No | W56: No
A57: 745048 | B57: 46245 | C57: DEPARTMENT OF FLEET AND FACILITY MANAGEMENT | D57: CHRISTY WEBBER LANDSCAPES | E57: TB/VJ/8 INVOICES/$14,513.78 | F57: 14513.78 | G57: 1. Pending New Contract - Original Contract Expired. New Contract in Process | H57: B. City Law Review | I57: APPROVED | J57: Yes | K57: No | M57: RX679137 | N57: E | O57: No linkage found in awarded contract file | T57: No | U57: No | V57: No | W57: Yes
A58: 727939 | B58: 46141 | C58: DEPARTMENT OF FLEET AND FACILITY MANAGEMENT | D58: C & C COMMUNICATIONS IL | E58: TB/CC/INVOICE #3371/$4495.20 | F58: 4495.2 | G58: 2. Pending Amendment/Modification - Line Item Addition / Vendor Limit Increase / Scope Change | H58: A. Specification Development Phase | I58: APPROVED | J58: No | K58: No | M58: RX710994 | N58: E | O58: No linkage found in awarded contract file | T58: No | U58: No | V58: No | W58: No
A59: 735722 | B59: 46189 | C59: DEPARTMENT OF FLEET AND FACILITY MANAGEMENT | D59: C & C COMMUNICATIONS IL | E59: TB/CC/INVOICE #3432/$17,103.61 | F59: 17103.61 | G59: 2. Pending Amendment/Modification - Line Item Addition / Vendor Limit Increase / Scope Change | H59: A. Specification Development Phase | I59: APPROVED | J59: No | K59: No | M59: RX710994 | N59: E | O59: No linkage found in awarded contract file | T59: No | U59: No | V59: No | W59: No
A60: 740007 | B60: 46216 | C60: DEPARTMENT OF FLEET AND FACILITY MANAGEMENT | D60: AGAE CONTRACTORS, INC. | E60: TB/AO/INVOICE #S3388-1/$418.50 | F60: 418.5 | G60: 1. Pending New Contract - Original Contract Expired. New Contract in Process | H60: C. Solicitation or Bidding Phase | I60: APPROVED | J60: Yes | K60: No | M60: RX607736 | N60: E | O60: No linkage found in awarded contract file | T60: No | U60: No | V60: No | W60: Yes
A61: 723320 | B61: 46119 | C61: DEPARTMENT OF FLEET AND FACILITY MANAGEMENT | D61: DIVERSE FACILITY SOLUTION INC. | E61: TB/AK/5 INVOICES/$684,994.42 | F61: 684994.42 | G61: 1. Pending New Contract - Original Contract Expired. New Contract in Process | H61: A. Specification Development Phase | I61: APPROVED | J61: Yes | K61: No | M61: RX624331 | N61: E | O61: No linkage found in awarded contract file | T61: No | U61: No | V61: No | W61: Yes
A62: 746487 | B62: 46253 | C62: DEPARTMENT OF FLEET AND FACILITY MANAGEMENT | D62: INDUSTRIAL FENCE INC. | E62: TB/AH/INVOICE #25453/$1903.10 | F62: 1903.1 | G62: 1. Pending New Contract - Original Contract Expired. New Contract in Process | H62: A. Specification Development Phase | I62: APPROVED | J62: No | K62: No | L62: TBD | M62: RX596048 | N62: E | O62: No linkage found in awarded contract file | T62: No | U62: No | V62: No | W62: No
A63: 721875 | B63: 46107 | C63: DEPARTMENT OF FLEET AND FACILITY MANAGEMENT | D63: INDUSTRIAL FENCE INC. | E63: TB/AH/INV #25467/$636.32 | F63: 636.32 | G63: 1. Pending New Contract - Original Contract Expired. New Contract in Process | H63: A. Specification Development Phase | I63: APPROVED | J63: No | K63: No | L63: TBD | M63: VDINDUSTRIAL FENCE | N63: E | O63: No linkage found in awarded contract file | T63: No | U63: No | V63: No | W63: No
A64: 711028 | B64: 46052 | C64: DEPARTMENT OF FLEET AND FACILITY MANAGEMENT | D64: CHARLES EQUIPMENT ENERGY SYSTEMS LLC | E64: TB/AH/INV#19054/$10,059.40 | F64: 10059.4 | G64: 1. Pending New Contract - Original Contract Expired. New Contract in Process | H64: A. Specification Development Phase | I64: APPROVED | J64: Yes | K64: No | M64: RX622326 | N64: E | O64: No linkage found in awarded contract file | T64: No | U64: No | V64: No | W64: Yes
A65: 735288 | B65: 46183 | C65: DEPARTMENT OF FLEET AND FACILITY MANAGEMENT | D65: WAREHOUSE DIRECT, INC. | E65: TB/GR/INV #6101269-0/$6272.00 | F65: 6272 | G65: 1. Pending New Contract - Original Contract Expired. New Contract in Process | H65: A. Specification Development Phase | I65: APPROVED | J65: Yes | K65: No | M65: RX677490 | N65: E | O65: No linkage found in awarded contract file | T65: No | U65: No | V65: No | W65: Yes
A66: 727971 | B66: 46141 | C66: DEPARTMENT OF FLEET AND FACILITY MANAGEMENT | D66: ARLINGTON GLASS & MIRROR | E66: TB/AO/INVOICE #75278/$4986.00 | F66: 4986 | G66: 1. Pending New Contract - Original Contract Expired. New Contract in Process | H66: A. Specification Development Phase | I66: APPROVED | J66: Yes | K66: No | M66: RX647383 | N66: E | O66: No linkage found in awarded contract file | T66: No | U66: No | V66: No | W66: Yes
A67: 737649 | B67: 46197 | C67: DEPARTMENT OF FLEET AND FACILITY MANAGEMENT | D67: PRESSURE WASHING SYSTEMS | E67: TB/MM/4 INVOICES/$4019.00 | F67: 4019 | G67: 1. Pending New Contract - Original Contract Expired. New Contract in Process | H67: B. City Law Review | I67: APPROVED | J67: Yes | K67: No | M67: RX717990 | N67: E | O67: No linkage found in awarded contract file | T67: No | U67: No | V67: No | W67: Yes
A68: 717839 | B68: 46087 | C68: DEPARTMENT OF FLEET AND FACILITY MANAGEMENT | D68: PRESSURE WASHING SYSTEMS | E68: TB/MM/2 INVOICES/$1353.00 | F68: 1353 | G68: 1. Pending New Contract - Original Contract Expired. New Contract in Process | H68: A. Specification Development Phase | I68: APPROVED | J68: Yes | K68: No | M68: RX708700 | N68: E | O68: No linkage found in awarded contract file | T68: No | U68: No | V68: No | W68: Yes
A69: 735025 | B69: 46182 | C69: DEPARTMENT OF FLEET AND FACILITY MANAGEMENT | D69: HEIDELBERG USA INC. | E69: TB/GR/2 INVOICES/$2999.00 | F69: 2999 | G69: 1. Pending New Contract - Original Contract Expired. New Contract in Process | H69: B. City Law Review | I69: APPROVED | J69: Yes | K69: No | L69: TBD | M69: RX617991 | N69: E | O69: No linkage found in awarded contract file | T69: No | U69: No | V69: No | W69: Yes
A70: 735635 | B70: 46189 | C70: DEPARTMENT OF FLEET AND FACILITY MANAGEMENT | D70: RUSH TRUCK CENTERS OF ILLINOIS INC | E70: TB/MM/INV #3045218396/$12,112.39 | F70: 12112.39 | G70: 1. Pending New Contract - Original Contract Expired. New Contract in Process | H70: B. City Law Review | I70: APPROVED | J70: Yes | K70: No | M70: RX590958 | N70: E | O70: No linkage found in awarded contract file | T70: No | U70: No | V70: No | W70: Yes
A71: 737617 | B71: 46197 | C71: DEPARTMENT OF FLEET AND FACILITY MANAGEMENT | D71: LIZZETTE MEDINA & COMPANY | E71: TB/VJ/4 INVOICES/$42,902.01 | F71: 42902.01 | G71: 1. Pending New Contract - Original Contract Expired. New Contract in Process | H71: B. City Law Review | I71: APPROVED | J71: Yes | K71: No | M71: RX652655 | N71: E | O71: No linkage found in awarded contract file | T71: No | U71: No | V71: No | W71: Yes
A72: 744428 | B72: 46241 | C72: DEPARTMENT OF FLEET AND FACILITY MANAGEMENT | D72: Eusebio Molina | E72: TB/JM/INVOICE #3931/$4000.00 | F72: 4000 | G72: 1. Pending New Contract - Original Contract Expired. New Contract in Process | H72: A. Specification Development Phase | I72: APPROVED | J72: No | K72: No | M72: RX742376 | N72: E | O72: No linkage found in awarded contract file | T72: No | U72: No | V72: No | W72: No
A73: 726255 | B73: 46136 | C73: DEPARTMENT OF FLEET AND FACILITY MANAGEMENT | D73: RUNNION EQUIPMENT CO | E73: TB/MM/8 INVOICES/$8427.63 | F73: 8427.63 | G73: 1. Pending New Contract - Original Contract Expired. New Contract in Process | H73: B. City Law Review | I73: APPROVED | J73: Yes | K73: No | M73: RX590958 | N73: E | O73: No linkage found in awarded contract file | T73: No | U73: No | V73: No | W73: Yes
A74: 725176 | B74: 46139 | C74: DEPARTMENT OF FLEET AND FACILITY MANAGEMENT | D74: CAR WASH PARTNERS INC | E74: TB/INV#9008/$13,057.00 | F74: 13057 | G74: 1. Pending New Contract - Original Contract Expired. New Contract in Process | H74: A. Specification Development Phase | I74: APPROVED | J74: Yes | K74: No | M74: RX710856 | N74: E | O74: No linkage found in awarded contract file | T74: No | U74: No | V74: No | W74: Yes
A75: 726239 | B75: 46136 | C75: DEPARTMENT OF FLEET AND FACILITY MANAGEMENT | D75: AGAE CONTRACTORS, INC. | E75: TB/AO/INV #S3384-1/$204.78 | F75: 204.78 | G75: 1. Pending New Contract - Original Contract Expired. New Contract in Process | H75: C. Solicitation or Bidding Phase | I75: APPROVED | J75: Yes | K75: No | M75: RX607736 | N75: E | O75: No linkage found in awarded contract file | T75: No | U75: No | V75: No | W75: Yes
A76: 725684 | B76: 46135 | C76: DEPARTMENT OF FLEET AND FACILITY MANAGEMENT | D76: ABC Humane Wildlife Control & Prevention, Inc. | E76: TB/AH/4 INVOICES/ $58,103.47 | F76: 58103.47 | G76: 1. Pending New Contract - Original Contract Expired. New Contract in Process | H76: A. Specification Development Phase | I76: APPROVED | J76: No | K76: No | M76: RX682957 | N76: E | O76: No linkage found in awarded contract file | T76: No | U76: No | V76: No | W76: No
A77: 729988 | B77: 46153 | C77: DEPARTMENT OF FLEET AND FACILITY MANAGEMENT | D77: 5410 Car Wash LLC | E77: TB/2 INVOICES/$2670.00 | F77: 2670 | G77: 1. Pending New Contract - Original Contract Expired. New Contract in Process | H77: A. Specification Development Phase | I77: APPROVED | J77: Yes | K77: No | M77: RX710856 | N77: E | O77: No linkage found in awarded contract file | T77: No | U77: No | V77: No | W77: Yes
A78: 746334 | B78: 46252 | C78: DEPARTMENT OF PROCUREMENT SERVICES | D78: BLUETRITON BRANDS INC | E78: Monthly Drinking Water Services at City of Chicago Salvage Operations August 2026 | F78: 29.97 | G78: 1. Pending New Contract - Original Contract Expired. New Contract in Process | H78: A. Specification Development Phase | I78: APPROVED | J78: Yes | K78: Yes | L78: 30043 | M78: RX511569 | N78: E | O78: No linkage found in awarded contract file | T78: No | U78: No | V78: No | W78: Yes
A79: 709701 | B79: 46045 | C79: DEPARTMENT OF STREETS AND SANITATION | D79: BLUETRITON BRANDS INC | E79: water | F79: 119.45 | G79: 6. Bid Protest - Contract Award under Review | H79: D. Solicitation Response Under Evaluation | I79: APPROVED | J79: Yes | K79: No | L79: 0 | M79: VDBLUETRITON BRANDS | N79: E | O79: No linkage found in awarded contract file | T79: No | U79: No | V79: No | W79: No
A80: 714990 | B80: 46072 | C80: DEPARTMENT OF STREETS AND SANITATION | D80: BLUETRITON BRANDS INC | E80: water | F80: 62.86 | G80: 6. Bid Protest - Contract Award under Review | H80: D. Solicitation Response Under Evaluation | I80: APPROVED | J80: Yes | K80: No | L80: 0 | M80: VDBLUETRITON BRANDS | N80: E | O80: No linkage found in awarded contract file | T80: No | U80: No | V80: No | W80: No
A81: 726038 | B81: 46136 | C81: DEPARTMENT OF STREETS AND SANITATION | D81: BLUETRITON BRANDS INC | E81: water | F81: 131.75 | G81: 6. Bid Protest - Contract Award under Review | H81: D. Solicitation Response Under Evaluation | I81: APPROVED | J81: Yes | K81: No | L81: 0 | M81: VDBLUETRITON BRANDS | N81: E | O81: No linkage found in awarded contract file | T81: No | U81: No | V81: No | W81: No
A82: 712306 | B82: 46058 | C82: CHICAGO DEPARTMENT OF PUBLIC HEALTH | D82: AVOQ LLC | E82: January 2025 Consulting Services CDPH MPV/HIVFebruary 2025 Consulting Services CDPH MPV/HIV | F82: 40000 | G82: 3. One Time Purchase | H82: H. One Time Purchase | I82: APPROVED | J82: Yes | K82: No | M82: VDAVOQ | N82: E | O82: No linkage found in awarded contract file | T82: No | U82: No | V82: No | W82: No
A83: 714588 | B83: 46077 | C83: CHICAGO DEPARTMENT OF AVIATION | D83: DTN, LLC | E83: Invoice# 210-00216719 SEPTEMBER 2025 Invoice Â¿ Used for visual representation of approaching weather to augment forecasting services. Also includes a pavement forecast, lightning monitoring and an approaching weather forecast. | F83: 3105 | G83: 5. User Dept. Decision - Elects to Purchase Smaller Goods or Services not Covered by Existing Contract | H83: A. Specification Development Phase | I83: APPROVED | J83: Yes | K83: No | M83: RX656425 | N83: E | O83: No linkage found in awarded contract file | T83: No | U83: No | V83: No | W83: Yes
A84: 736858 | B84: 46195 | C84: CHICAGO DEPARTMENT OF AVIATION | D84: R4 SERVICES, LLC. | E84: #3 Invoices $7,434.75NEED TO PAY RECURRING INVOICES FOR RECORDS RETENTIONSERVICES 3/26, 4/26, 5/26 | F84: 7434.75 | G84: 2. Pending Amendment/Modification - Line Item Addition / Vendor Limit Increase / Scope Change | H84: A. Specification Development Phase | I84: APPROVED | J84: No | K84: No | M84: VDR4 | N84: E | O84: No linkage found in awarded contract file | T84: No | U84: No | V84: No | W84: No
A85: 729536 | B85: 46163 | C85: CHICAGO DEPARTMENT OF AVIATION | D85: VALDES LLC | E85: Invoice# 112505 2026 Midway Deicing Materials - Magnesium Chloride 50lb bag. To pay invoice # 112505 | F85: 27965 | G85: 1. Pending New Contract - Original Contract Expired. New Contract in Process | H85: A. Specification Development Phase | I85: APPROVED | J85: No | K85: No | M85: RX687026 | N85: E | O85: No linkage found in awarded contract file | T85: No | U85: No | V85: No | W85: No
A86: 737893 | B86: 46203 | C86: DEPARTMENT OF FLEET AND FACILITY MANAGEMENT | D86: RUNNION EQUIPMENT CO | E86: Runnion Equipment 743464 B JS/ MM/ Invoice # INV68694/ $3,056.12/ AVCB01/ WO 2619174/ Aerial Inspection & Certification | F86: 3056.12 | G86: 1. Pending New Contract - Original Contract Expired. New Contract in Process | H86: B. City Law Review | I86: APPROVED | J86: Yes | K86: No | M86: RX590958 | N86: E | O86: No linkage found in awarded contract file | T86: No | U86: No | V86: No | W86: Yes
A87: 741044 | B87: 46238 | C87: DEPARTMENT OF FLEET AND FACILITY MANAGEMENT | D87: EQUIPMENT DEPOT OF ILLINOIS INC | E87: Equipment Depot of Illinois, Inc. 50081462 G JS/ WW/ Invoice # 1300174268/ $136,232.00/2 DUA FUEL FORKLIFTS 900 E. 10RD | F87: 136232 | G87: 1. Pending New Contract - Original Contract Expired. New Contract in Process | H87: A. Specification Development Phase | I87: APPROVED | J87: No | K87: No | M87: RX738666 | N87: E | O87: No linkage found in awarded contract file | T87: No | U87: No | V87: No | W87: No
A88: 722200 | B88: 46142 | C88: DEPARTMENT OF FLEET AND FACILITY MANAGEMENT | D88: HASTINGS AIR ENERGY CONTROL | E88: Hastings 1033282 B JS/ JG/ Invoice Number: O38604D102-B/ $3,451.50/ January / Exhaust System Maint Pt. 2 | F88: 3451.5 | G88: 2. Pending Amendment/Modification - Line Item Addition / Vendor Limit Increase / Scope Change | H88: A. Specification Development Phase | I88: APPROVED | J88: No | K88: Yes | L88: 112351 | M88: RX721077 | N88: E | O88: No linkage found in awarded contract file | T88: No | U88: No | V88: No | W88: No
A89: 733531 | B89: 46189 | C89: DEPARTMENT OF FLEET AND FACILITY MANAGEMENT | D89: HASTINGS AIR ENERGY CONTROL | E89: Hastings Air-Energy 1033282 B JS/ JG/ Invoice No. O38604D105/ $56,691.64/ April / Exhaust System Maint | F89: 56691.64 | G89: 2. Pending Amendment/Modification - Line Item Addition / Vendor Limit Increase / Scope Change | H89: A. Specification Development Phase | I89: APPROVED | J89: No | K89: Yes | L89: 112351 | M89: RX724184 | N89: E | O89: No linkage found in awarded contract file | T89: No | U89: No | V89: No | W89: No
A90: 707746 | B90: 46031 | C90: DEPARTMENT OF FLEET AND FACILITY MANAGEMENT | D90: A SAFE HAVEN FOUNDATION | E90: A Safe Haven 50074290 A JS/ AH/ 4 INVOICES/ $67,254.39/ Past Due Invoices | F90: 67254.39 | G90: 1. Pending New Contract - Original Contract Expired. New Contract in Process | H90: B. City Law Review | I90: APPROVED | J90: Yes | K90: No | M90: RX596443 | N90: E | O90: No linkage found in awarded contract file | T90: No | U90: No | V90: No | W90: Yes
A91: 721575 | B91: 46107 | C91: DEPARTMENT OF FLEET AND FACILITY MANAGEMENT | D91: AGAE CONTRACTORS, INC. | E91: AGAE Contractors 50570038 A JS/ WA/ Invoice Number 3344-1/ $2,577.59/ WO 5234585/ Signs needed for parking lot | F91: 2577.59 | G91: 1. Pending New Contract - Original Contract Expired. New Contract in Process | H91: C. Solicitation or Bidding Phase | I91: APPROVED | J91: Yes | K91: No | M91: RX607736 | N91: E | O91: No linkage found in awarded contract file | T91: No | U91: No | V91: No | W91: Yes
A92: 718160 | B92: 46087 | C92: DEPARTMENT OF FLEET AND FACILITY MANAGEMENT | D92: ZIPCAR INC | E92: ZIPCAR 54117025 - C JS/ WW/ 10-INVS/ $1,943.08/ DECEMBER 2025 CHARGES | F92: 1943.08 | G92: 1. Pending New Contract - Original Contract Expired. New Contract in Process | H92: B. City Law Review | I92: APPROVED | J92: No | K92: No | M92: RX529316 | N92: E | O92: No linkage found in awarded contract file | T92: No | U92: No | V92: No | W92: No
A93: 734256 | B93: 46181 | C93: DEPARTMENT OF FLEET AND FACILITY MANAGEMENT | D93: ZIPCAR INC | E93: ZIPCZR 54117025 - CJS/ WW/ 9-INVOICES/ $4,040.56/ APRIL 2026 CHARGES | F93: 4040.56 | G93: 1. Pending New Contract - Original Contract Expired. New Contract in Process | H93: B. City Law Review | I93: APPROVED | J93: No | K93: No | M93: RX529316 | N93: E | O93: No linkage found in awarded contract file | T93: No | U93: No | V93: No | W93: No
A94: 720685 | B94: 46107 | C94: DEPARTMENT OF FLEET AND FACILITY MANAGEMENT | D94: DAYSPRING PROFESSIONAL JANITOR | E94: DAYSPRING 51588021 A JS/ AH/ 8-INV/ $449,111.74/ JAN 2FM | F94: 449111.74 | G94: 1. Pending New Contract - Original Contract Expired. New Contract in Process | H94: A. Specification Development Phase | I94: APPROVED | J94: Yes | K94: No | M94: RX624331 | N94: E | O94: No linkage found in awarded contract file | T94: No | U94: No | V94: No | W94: Yes
A95: 717940 | B95: 46086 | C95: DEPARTMENT OF FLEET AND FACILITY MANAGEMENT | D95: P. R. STREICH & SONS | E95: PR Streich 835755 A JS/ MM/ Invoice # 57112/ $11,627.38/ WO 2554702 | F95: 11627.38 | G95: 1. Pending New Contract - Original Contract Expired. New Contract in Process | H95: B. City Law Review | I95: APPROVED | J95: Yes | K95: No | L95: TBD | M95: RX679901 | N95: E | O95: No linkage found in awarded contract file | T95: No | U95: No | V95: No | W95: Yes
A96: 743734 | B96: 46238 | C96: DEPARTMENT OF FLEET AND FACILITY MANAGEMENT | D96: CHARLES EQUIPMENT ENERGY SYSTEMS LLC | E96: Charles Equipment 157247 A JS/ CE/ Invoice 19473/ $826.00/ June 2026/ Repair and Maintenance | F96: 826 | G96: 1. Pending New Contract - Original Contract Expired. New Contract in Process | H96: A. Specification Development Phase | I96: APPROVED | J96: Yes | K96: No | M96: RX622326 | N96: E | O96: No linkage found in awarded contract file | T96: No | U96: No | V96: No | W96: Yes
A97: 738152 | B97: 46203 | C97: DEPARTMENT OF FLEET AND FACILITY MANAGEMENT | D97: ABC Humane Wildlife Control & Prevention, Inc. | E97: ABC Humane 57046423 A JS/ VJ/ 10-Invoices/ $79,812.79/ May 2026/ 2FM | F97: 79812.79 | G97: 1. Pending New Contract - Original Contract Expired. New Contract in Process | H97: A. Specification Development Phase | I97: APPROVED | J97: No | K97: No | M97: RX682957 | N97: E | O97: No linkage found in awarded contract file | T97: No | U97: No | V97: No | W97: No
A98: 737833 | B98: 46203 | C98: DEPARTMENT OF FLEET AND FACILITY MANAGEMENT | D98: Helicopters, Inc. | E98: Helicopter Inc. 10633647 A JS/ BJ/ 2-Invoices/ $18,497.54/ PD911Q/ WO 2626555/ ASR/50 HR inspection due and 150 hr engine inspection due | F98: 18497.54 | G98: 1. Pending New Contract - Original Contract Expired. New Contract in Process | H98: B. City Law Review | I98: APPROVED | J98: Yes | K98: No | L98: TBD | M98: RX690671 | N98: A | O98: Requisition ID link: Exhibit B new-contract RX = awarded REQ | P98: 386844 | Q98: Helicopters, Inc. | R98: 46203 | S98: EMERGENCY | T98: No | U98: No | V98: Yes | W98: Yes
A99: 711725 | B99: 46052 | C99: CHICAGO POLICE DEPARTMENT | D99: Service Sanitation Inc. | E99: Service Sanitation Inv 9090265 $1,250 | F99: 1250 | G99: 1. Pending New Contract - Original Contract Expired. New Contract in Process | H99: A. Specification Development Phase | I99: APPROVED | J99: No | K99: No | M99: RX613315 | N99: A | O99: Requisition ID link: Exhibit B new-contract RX = awarded REQ | P99: 381051 | Q99: Service Sanitation Inc. | R99: 46203 | S99: BID | T99: Yes | U99: Yes | V99: No | W99: No
A100: 746762 | B100: 46253.667 | C100: DEPARTMENT OF PLANNING AND DEVELOPMENT | D100: COSTAR REALTY INFORMATION, INC | E100: CoStar Aug 2026 Invoice | F100: 7906.6 | K100: No | M100: VDCOSTAR REALTY INFORMATION | N100: E | O100: No linkage found in awarded contract file | T100: No | U100: No | V100: No | W100: No
...

Sheet Awarded Contracts
A1: Contract ID | B1: PO | C1: Requisition | D1: Spec | E1: Description | F1: Vendor | G1: Department | H1: Unit | I1: Award Date | J1: Start Date | K1: Award Amount | L1: Procurement Type | M1: Competitive | N1: Contract Type | O1: Type | P1: Buyer | Q1: Days to Award
A2: 358966 | B2: 311043 | C2: 305813 | D2: 1191270 | E2: Radio Communications Equipment and Compatibility for Parts, Repairs, Software, Installation Services and Accessories | F2: MOTOROLA SOLUTIONS INC | G2: 51 - OFFICE OF PUBLIC SAFETY ADMINISTRATION | H2: PROFESSIONAL SERVICES | I2: 46052 | J2: 2019-10-22 | K2: 65000000 | L2: RFP | M2: Yes | N2: PRO SERV CONSULTING $250,000orABOVE | O2: BLANKET | P2: CLARK, LISA M | Q2: 2292
A3: 385229 | B3: 317980 | C3: 676037 | D3: 1328245 | E3: Travel Management Services | F3: Corporate Travel Management North America, Inc. | G3: 05 - OFFICE OF BUDGET & MANAGEMENT | H3: PROFESSIONAL SERVICES | I3: 46247 | J3: 2025-07-02 | K3: 60000 | L3: REFERENCE CONTRACT | M3: No | N3: PRO SERV CONSULTING $250,000orABOVE | O3: BLANKET | P3: CALDERA, LISBET A | Q3: 407
A4: 383774 | B4: 325156 | C4: 617787 | D4: 1305042 | E4: 1305042: DWM JOC Civil, Structural and Architectural Disciplines | F4: Construction Inc | G4: 88 - DEPARTMENT OF WATER MANAGEMENT | H4: CONSTRUCTION | I4: 46045 | J4: 2024-08-14 | K4: 15000000 | L4: BID | M4: Yes | N4: JOC | O4: BLANKET | P4: SZYMUSIAK, DIANE | Q4: 527
A5: 383771 | B5: 325159 | C5: 618945 | D5: 1305046 | E5: 1305046: DWM JOC Mechanical, Electrical and Plumbing Disciplines | F5: Construction Inc | G5: 88 - DEPARTMENT OF WATER MANAGEMENT | H5: CONSTRUCTION | I5: 46045 | J5: 2024-08-20 | K5: 15000000 | L5: BID | M5: Yes | N5: JOC | O5: BLANKET | P5: SZYMUSIAK, DIANE | Q5: 521
A6: 386406 | B6: 325474 | C6: 664689 | D6: 1324140 | E6: Legislative Consulting Services in Springfield, IL for the City of Chicago | F6: LKP CONSULTING LLC | G6: 01 - OFFICE OF THE MAYOR | H6: PROFESSIONAL SERVICES | I6: 46024 | J6: 2025-09-30 | K6: 48000 | L6: SOLE SOURCE | M6: No | N6: PRO SERV CONSULTING UNDER $250,000 | O6: BLANKET | P6: CALLAHAN, PATRICK M | Q6: 94
A7: 383851 | B7: 325900 | C7: 505441 | D7: 1263403 | E7: Sewer Main Lining Program - PN7589B North Area (IEPA) | F7: SAK CONSTRUCTION LLC | G7: 88 - DEPARTMENT OF WATER MANAGEMENT | H7: CONSTRUCTION | I7: 46057 | J7: 2025-03-18 | K7: 29433070 | L7: BID | M7: Yes | N7: CONSTRUCTION-LARGE $3MILLIONorABOVE | O7: BLANKET | P7: WILLINGHAM, ANTONIO | Q7: 323
A8: 383852 | B8: 325902 | C8: 505445 | D8: 1263405 | E8: Sewer Main Lining Program - PN7589D South Area (IEPA) | F8: SAK CONSTRUCTION LLC | G8: 88 - DEPARTMENT OF WATER MANAGEMENT | H8: CONSTRUCTION | I8: 46057 | J8: 2025-03-18 | K8: 27487950 | L8: BID | M8: Yes | N8: CONSTRUCTION-LARGE $3MILLIONorABOVE | O8: BLANKET | P8: WILLINGHAM, ANTONIO | Q8: 323
A9: 380107 | B9: 328515 | C9: 595897 | D9: 1297124 | E9: Ring Tunnel Electrical And Lighting Infrastructure at O'Hare International Airport | F9: COURTESY ELECTRIC INC | G9: 85 - CHICAGO DEPARTMENT OF AVIATION | H9: AVIATION | I9: 46059 | J9: 2024-04-18 | K9: 6740001 | L9: BID | M9: Yes | N9: CONSTRUCTION-AVIATION | O9: STANDARD | P9: KUSPER, CHRISTOPHER J | Q9: 659
A10: 375509 | B10: 329774 | C10: 530823 | D10: 1232177 | E10: Group B: Purchase of FAA Approved Portable Runway Friction Testing Decelerometers and Continuous Friction Measuring Equipment (CFME) Including Parts, Service, Training and Calibration | F10: Halliday Technologies | G10: 85 - CHICAGO DEPARTMENT OF AVIATION | H10: AVIATION | I10: 46106 | J10: 2023-05-19 | K10: 2542840.1 | L10: BID | M10: Yes | N10: WORK SERV-AVIATION | O10: BLANKET | P10: MAGNO, THOMAS | Q10: 1041
A11: 386724 | B11: 331048 | C11: 664680 | D11: 1324136 | E11: Legislative Consulting Services | F11: VINCENT R. WILLIAMS & ASSOCIATES P.C. | G11: 01 - OFFICE OF THE MAYOR | H11: PROFESSIONAL SERVICES | I11: 46024 | J11: 2025-10-17 | K11: 72000 | L11: SOLE SOURCE | M11: No | N11: PRO SERV CONSULTING UNDER $250,000 | O11: BLANKET | P11: CALLAHAN, PATRICK M | Q11: 77
A12: 386726 | B12: 331077 | C12: 664700 | D12: 1256622 | E12: Legislative Consulting Services | F12: BLAIDA AND ASSOCIATES LLC | G12: 01 - OFFICE OF THE MAYOR | H12: PROFESSIONAL SERVICES | I12: 46024 | J12: 2025-10-17 | K12: 97999.92 | L12: SOLE SOURCE | M12: No | N12: PRO SERV CONSULTING UNDER $250,000 | O12: BLANKET | P12: CALLAHAN, PATRICK M | Q12: 77
A13: 386725 | B13: 331094 | C13: 664139 | D13: 1324130 | E13: Legislative Consulting Services | F13: THE BASS GROUP INC | G13: 01 - OFFICE OF THE MAYOR | H13: PROFESSIONAL SERVICES | I13: 46024 | J13: 2025-04-28 | K13: 48000 | L13: SOLE SOURCE | M13: No | N13: PRO SERV CONSULTING UNDER $250,000 | O13: BLANKET | P13: CALLAHAN, PATRICK M | Q13: 249
... A26: 384808 | B26: 336341 | C26: 660057 | D26: 1322498 | E26: 1322498: ASSET and TREES INVENTORY MANAGEMENT | F26: ArborPro, Inc | G26: 81 - DEPARTMENT OF STREETS AND SANITATION | H26: WORK SERVICES | I26: 46107 | J26: 2025-06-03 | K26: 2537000 | L26: RFP | M26: Yes | N26: WORK SERVICES / FACILITIES MAINT. | O26: BLANKET | P26: POLK-STAMPS, MELANIE L | Q26: 264
A27: 387773 | B27: 336347 | D27: 1285012 | E27: PO 336347 replacing PO 326503: 21-203 Sawyer Water Purification Plant (SWPP) Sinkhole Repairs | F27: Michels Construction, Inc. | G27: 88 - DEPARTMENT OF WATER MANAGEMENT | H27: CONSTRUCTION | I27: 46170 | J27: 2026-01-09 | K27: 7336323 | L27: CONTRACT ASSIGNMENT/TRANSFER | M27: No | N27: CONSTRUCTION-LARGE $3MILLIONorABOVE | O27: STANDARD | P27: SZYMUSIAK, DIANE | Q27: 139
A28: 387728 | B28: 336809 | C28: 702748 | D28: 450998 | E28: DLT Quote# 5331551 for Time and Materials Services. | F28: DLT SOLUTIONS LLC | G28: 06 - DEPARTMENT OF TECHNOLOGY AND INNOVATION | H28: PROFESSIONAL SERVICES | I28: 46073 | J28: 2026-01-07 | K28: 48673.35 | L28: JOINT PURCHASE | M28: No | N28: SOFTWARE | O28: STANDARD | P28: CORTES, ANN C | Q28: 44
A29: 383993 | B29: 337037 | C29: 653063 | D29: 1276708C | E29: Maintenance, Parts and Repair Services for The Cambridge Axle Scale | F29: ABEST SCALE CO., INC. | G29: 35 - DEPARTMENT OF PROCUREMENT SERVICES | H29: SMALL ORDERS | I29: 46063 | J29: 2025-04-08 | K29: 22300 | L29: BID | M29: Yes | N29: WORK SERVICES-SMALL ORDERS | O29: BLANKET | P29: HARGES, BERNIE D | Q29: 308
A30: 383808 | B30: 337490 | C30: 654367 | D30: 1258048A | E30: Spec 1258048A: Term Agreement for Water Main Construction and Lead Service Line Replacement: CBD/City Wide Specialty Contract - District Four (re-bid) | F30: RELIABLE CONTRACTING AND EQUIPMENT COMPANY | G30: 88 - DEPARTMENT OF WATER MANAGEMENT | H30: CONSTRUCTION | I30: 46142 | J30: 2025-03-07 | K30: 42956888 | L30: BID | M30: Yes | N30: CONSTRUCTION-LARGE $3MILLIONorABOVE | O30: BLANKET | P30: PESHOFF, NANCY R | Q30: 419
A31: 383513 | B31: 338805 | C31: 652517 | D31: 1302011 | E31: 1302011: Neighborhood Capital Improvement Contract (NCI) South and West Area | F31: SEVEN D CONSTRUCTION COMPANY | G31: 84 - CHICAGO DEPARTMENT OF TRANSPORTATION | H31: CONSTRUCTION | I31: 46107 | J31: 2025-02-26 | K31: 35350588 | L31: BID | M31: Yes | N31: CONSTRUCTION-LARGE $3MILLIONorABOVE | O31: BLANKET | P31: BEJAR, LUIS | Q31: 393
A32: 383509 | B32: 338920 | C32: 652520 | D32: 1302006 | E32: 1302006 Neighborhood Capital Improvement Contract (NCI) - North Area | F32: G & V CONSTRUCTION CO INC | G32: 84 - CHICAGO DEPARTMENT OF TRANSPORTATION | H32: CONSTRUCTION | I32: 46094 | J32: 2025-02-26 | K32: 43755352 | L32: BID | M32: Yes | N32: CONSTRUCTION-LARGE $3MILLIONorABOVE | O32: BLANKET | P32: BEJAR, LUIS | Q32: 380
A33: 383508 | B33: 338941 | C33: 652829 | D33: 1302007 | E33: 1302007 Neighborhood Capital Improvement Contract (NCI) - Central Area | F33: SUMIT CONSTRUCTION CO., INC. | G33: 84 - CHICAGO DEPARTMENT OF TRANSPORTATION | H33: CONSTRUCTION | I33: 46094 | J33: 2025-02-27 | K33: 46954295 | L33: BID | M33: Yes | N33: CONSTRUCTION-LARGE $3MILLIONorABOVE | O33: BLANKET | P33: BEJAR, LUIS | Q33: 379
A34: 386108 | B34: 339016 | C34: 675346 | D34: 1327949 | E34: Spec 1327949, West Taxiways Development at Chicago O'Hare International Airport, Federal | F34: FH PASCHEN SN NIELSEN & ASSOCIATES LLC | G34: 85 - CHICAGO DEPARTMENT OF AVIATION | H34: AVIATION | I34: 46087 | J34: 2025-06-30 | K34: 87378396 | L34: BID | M34: Yes | N34: CONSTRUCTION-AVIATION | O34: STANDARD | P34: MAGNO, THOMAS | Q34: 249
A35: 388093 | B35: 339236 | D35: 1097939 | E35: Transfer from PO#157717 MULTI-FUNCTION DEVICES (MFDS), PRINTERS, AND RELATED SERVICES | F35: CANON U.S.A., INC | G35: 38 - DEPARTMENT OF FLEET AND FACILITY MANAGEMENT | H35: WORK SERVICES | I35: 46064 | J35: 2026-02-06 | K35: 4334711.4 | L35: CONTRACT ASSIGNMENT/TRANSFER | M35: No | N35: WORK SERVICES / FACILITIES MAINT. | O35: BLANKET | P35: HARRISON-BONNER, KENYA D | Q35: 5
A36: 388075 | B36: 339754 | D36: 137797 | E36: TRANSFERRED FROM PO 241988 TERM AGREEMENTS FOR CONSTRUCTION MANAGEMENT SERVICES NON-TARGET MARKET | F36: GFT Infrastructure, Inc. | G36: 88 - DEPARTMENT OF WATER MANAGEMENT | H36: ARCH & ENGINEERING | I36: 46058 | J36: 2026-02-04 | K36: 3307227.9 | L36: CONTRACT ASSIGNMENT/TRANSFER | M36: No | N36: ARCH/ENGINEERING | O36: BLANKET | P36: UDAIYAR, VENKATESH | Q36: 1
A37: 388026 | B37: 339835 | C37: 710537 | D37: 450998 | E37: DLT Quote# 5349655 for Oracle PaaS and IaaS Universal Credits. | F37: DLT SOLUTIONS LLC | G37: 06 - DEPARTMENT OF TECHNOLOGY AND INNOVATION | H37: PROFESSIONAL SERVICES | I37: 46094 | J37: 2026-01-30 | K37: 1082000 | L37: JOINT PURCHASE | M37: No | N37: SOFTWARE | O37: STANDARD | P37: CORTES, ANN C | Q37: 42
A38: 388017 | B38: 339842 | C38: 711058 | D38: 450998 | E38: DLT Quote# 5331549 for Oracle iProcurement, iSupplier, Procurement, Sourcing for Purchasing and Supplier Lifecycle. | F38: DLT SOLUTIONS LLC | G38: 06 - DEPARTMENT OF TECHNOLOGY AND INNOVATION | H38: PROFESSIONAL SERVICES | I38: 46094 | J38: 2026-01-29 | K38: 77964.03 | L38: JOINT PURCHASE | M38: No | N38: SOFTWARE | O38: STANDARD | P38: CORTES, ANN C | Q38: 43
A39: 388030 | B39: 339844 | C39: 711376 | D39: 450998 | E39: DLT Quote# 5363936 for Oracle iProcurement, iSupplier, Procurement, Sourcing for Purchasing and Supplier Lifecycle. | F39: DLT SOLUTIONS LLC | G39: 06 - DEPARTMENT OF TECHNOLOGY AND INNOVATION | H39: PROFESSIONAL SERVICES | I39: 46094 | J39: 2026-01-30 | K39: 80347.36 | L39: JOINT PURCHASE | M39: No | N39: SOFTWARE | O39: STANDARD | P39: CORTES, ANN C | Q39: 42
A40: 388081 | B40: 339915 | D40: 129543 | E40: TRANSFERRED FROM PO38958 - MASTER TASK ORDER CONTRACT FOR CONSULTING SERVICES AGREEMENT FOR SURFACE TRANSPORTATION PLANNING STUDIES CATEGORIES 1-5: AWARDED CATEGORIES ONE, TWO, AND FOUR | F40: GFT Infrastructure, Inc. | G40: 84 - CHICAGO DEPARTMENT OF TRANSPORTATION | H40: ARCH & ENGINEERING | I40: 46063 | J40: 2026-02-05 | K40: 4595682.2 | L40: CONTRACT ASSIGNMENT/TRANSFER | M40: No | N40: ARCH/ENGINEERING | O40: BLANKET | P40: UDAIYAR, VENKATESH | Q40: 5
A41: 388110 | B41: 339918 | D41: 1155535 | E41: TRANSFERED FROM PO 179220 RFQ FOR PROFESSIONAL DESIGN ENGINEERING SERVICES FOR 92ND STREET BASCULE BRIDGE OVER THE CALUMET RIVER - CDOT PROJECT NO. E-7-479 | F41: GFT Infrastructure, Inc. | G41: 84 - CHICAGO DEPARTMENT OF TRANSPORTATION | H41: ARCH & ENGINEERING | I41: 46064 | J41: 2026-02-09 | K41: 596256.4 | L41: CONTRACT ASSIGNMENT/TRANSFER | M41: No | N41: ARCH/ENGINEERING | O41: BLANKET | P41: UDAIYAR, VENKATESH | Q41: 2
A42: 388473 | B42: 341673 | C42: 708161 | D42: 1325082 | E42: Purchase of Multi-Purpose Snow Removal Equipment for Midway and O'Hare | F42: Boschung America, LLC | G42: 85 - CHICAGO DEPARTMENT OF AVIATION | H42: AVIATION | I42: 46118 | J42: 2026-01-12 | K42: 120000000 | L42: REFERENCE CONTRACT | M42: No | N42: WORK SERV-AVIATION | O42: BLANKET | P42: DUKE, KARL D | Q42: 84
A43: 386844 | B43: 342138 | C43: 690671 | D43: 1334021 | E43: EMERGENCY CONTRACT FOR PARTS, LABOR, REPAIR, MAINTENANCE, ACCESSORIES, AND SUPPLIES TO OPERATE CITY-OWNED BELL HELICOPTERS | F43: Helicopters, Inc. | G43: 38 - DEPARTMENT OF FLEET AND FACILITY MANAGEMENT | H43: WORK SERVICES | I43: 46203 | J43: 2025-10-27 | K43: 1000000 | L43: EMERGENCY | M43: No | N43: WORK SERVICES / FACILITIES MAINT. | O43: BLANKET | P43: HARGES, BERNIE D | Q43: 246
A44: 379869 | B44: 342332 | C44: 589357 | D44: 1295019 | E44: 1295019: Rescue Tools - Equipment, Parts, Accessories and Repairs | F44: ROOT BROS MFG & SUPPLY CO | G44: 59 - CHICAGO FIRE DEPARTMENT | H44: WORK SERVICES | I44: 46111 | J44: 2024-05-06 | K44: 5823500 | L44: BID | M44: Yes | N44: WORK SERVICES / FACILITIES MAINT. | O44: BLANKET | P44: PIPERCANON, KIMBERLY | Q44: 532
A45: 383514 | B45: 342773 | C45: 652632 | D45: 1302008 | E45: 1302008: Neighborhood Capital Improvement Contract (NCI) Southeast Area | F45: MQ SEWER & WATER CONTRACTORS | G45: 84 - CHICAGO DEPARTMENT OF TRANSPORTATION | H45: CONSTRUCTION | I45: 46136 | J45: 2025-02-27 | K45: 58759820 | L45: BID | M45: Yes | N45: CONSTRUCTION-LARGE $3MILLIONorABOVE | O45: BLANKET | P45: BEJAR, LUIS | Q45: 421
A46: 380472 | B46: 343120 | C46: 600764 | D46: 1298971 | E46: Combined Heat Exchanger Projects at O'Hare International Airport (SBI-1) | F46: AUTUMN CONSTRUCTION SERVICES, INC. | G46: 85 - CHICAGO DEPARTMENT OF AVIATION | H46: AVIATION | I46: 46151 | J46: 2024-06-21 | K46: 10647000 | L46: BID | M46: Yes | N46: CONSTRUCTION-AVIATION | O46: STANDARD | P46: KUSPER, CHRISTOPHER J | Q46: 607
A47: 381210 | B47: 343540 | C47: 612193 | D47: 1303031 | E47: PAVEMENT STRIPING OF RUNWAYS, TAXIWAYS AND ROADWAYS FOR THE CHICAGO DEPARTMENT OF AVIATION (SPEC NO. 1303031) | F47: PREFORM TRAFFIC CONTROL SYSTEM, LTD | G47: 85 - CHICAGO DEPARTMENT OF AVIATION | H47: AVIATION | I47: 46106 | J47: 2024-08-19 | K47: 70636290 | L47: BID | M47: Yes | N47: WORK SERV-AVIATION | O47: BLANKET | P47: DUKE, KARL D | Q47: 583
A48: 388280 | B48: 343953 | C48: 712805 | D48: 450998 | E48: DLT Quote # 5386238 for Oracle Custom Fixed Service. | F48: DLT SOLUTIONS LLC | G48: 06 - DEPARTMENT OF TECHNOLOGY AND INNOVATION | H48: PROFESSIONAL SERVICES | I48: 46153 | J48: 2026-02-23 | K48: 148387 | L48: JOINT PURCHASE | M48: No | N48: SOFTWARE | O48: STANDARD | P48: CORTES, ANN C | Q48: 77
A49: 383127 | B49: 344066 | C49: 630858 | D49: 1310217 | E49: Economy Garage Lighting Replacement (SBI) at Midway International Airport | F49: COURTESY ELECTRIC INC | G49: 85 - CHICAGO DEPARTMENT OF AVIATION | H49: AVIATION | I49: 46217 | J49: 2025-01-27 | K49: 3255010.6 | L49: BID | M49: Yes | N49: CONSTRUCTION-AVIATION | O49: STANDARD | P49: MERRICK, TOBY | Q49: 524
A50: 387053 | B50: 344340 | C50: 697512 | D50: 1303936A | E50: 1303936A: DIVISION STREET STREETSCAPE W Division Street, N. Dearborn Street to N. State Street | F50: Rausch Infrastructure LLC | G50: 84 - CHICAGO DEPARTMENT OF TRANSPORTATION | H50: CONSTRUCTION | I50: 46136 | J50: 2025-11-10 | K50: 2499602.5 | L50: BID | M50: Yes | N50: CONSTRUCTION-LARGE $3MILLIONorABOVE | O50: STANDARD | P50: PESHOFF, NANCY R | Q50: 165
A51: 388384 | B51: 344423 | C51: 717479 | D51: 1345340 | E51: Temporary Medical Personnel Emergency Procurement. | F51: McKinley and Company Recruitment, Inc. | G51: 41 - CHICAGO DEPARTMENT OF PUBLIC HEALTH | H51: PROFESSIONAL SERVICES | I51: 46153 | J51: 2026-03-04 | K51: 1000000 | L51: EMERGENCY | M51: No | N51: PRO SERV CONSULTING $250,000orABOVE | O51: STANDARD | P51: CORTES, ANN C | Q51: 68
A52: 385651 | B52: 344574 | C52: 677687 | D52: 1330319 | E52: MAINTENANCE, REPAIR AND INSTALLATION OF TERRAZZO (SPEC #1330319) | F52: MCDONAGH DEMOLITION, INC. | G52: 85 - CHICAGO DEPARTMENT OF AVIATION | H52: AVIATION | I52: 46177 | J52: 2025-07-11 | K52: 33934429 | L52: BID | M52: Yes | N52: WORK SERV-AVIATION | O52: BLANKET | P52: DUKE, KARL D | Q52: 328
A53: 388284 | B53: 345203 | C53: 715111 | D53: 134400 | E53: REFERENCE AGREEMENT THROUGH REGION 14 ESC & OMNIA PARTNERS FOR | F53: ERNST & YOUNG LLP | G53: 05 - OFFICE OF BUDGET & MANAGEMENT | H53: PROFESSIONAL SERVICES | I53: 46107 | J53: 2026-02-19 | K53: 6720000 | L53: REFERENCE CONTRACT | M53: No | N53: PRO SERV CONSULTING $250,000orABOVE | O53: BLANKET | P53: RICHY, MICHAEL A | Q53: 35
A54: 385131 | B54: 345303 | C54: 673005 | D54: 1316093 | E54: 1316093: CATALPA AVENUE PLAZA IMPROVEMENTS, CDOT PROJECT NO.: S-1-409 | F54: SUMIT CONSTRUCTION CO., INC. | G54: 84 - CHICAGO DEPARTMENT OF TRANSPORTATION | H54: CONSTRUCTION | I54: 46127 | J54: 2025-06-16 | K54: 2739500.5 | L54: BID | M54: Yes | N54: CONSTRUCTION-LARGE $3MILLIONorABOVE | O54: STANDARD | P54: PESHOFF, NANCY R | Q54: 303
A55: 387744 | B55: 345544 | C55: 707745 | D55: 1316729 | E55: 1316729: 92nd Street Bascule Bridge of the Calumet River Rehabilitation | F55: FH PASCHEN SN NIELSEN & ASSOCIATES LLC | G55: 84 - CHICAGO DEPARTMENT OF TRANSPORTATION | H55: CONSTRUCTION | I55: 46241 | J55: 2026-01-08 | K55: 1.3506395e+08 | L55: BID | M55: Yes | N55: CONSTRUCTION-LARGE $3MILLIONorABOVE | O55: STANDARD | P55: PESHOFF, NANCY R | Q55: 211
A56: 384233 | B56: 345601 | C56: 662082 | D56: 1292540A | E56: 1292540A: Sewer Cleaning and Televising Services (Groups - North, Central, and South Areas) Groups | F56: NATIONAL POWER RODDING CORP | G56: 88 - DEPARTMENT OF WATER MANAGEMENT | H56: WORK SERVICES | I56: 46134 | J56: 2025-04-22 | K56: 68291000 | L56: BID | M56: Yes | N56: WORK SERVICES / FACILITIES MAINT. | O56: BLANKET | P56: POLK-STAMPS, MELANIE L | Q56: 365
A57: 376209 | B57: 345942 | C57: 534299 | D57: 1274349 | E57: Solid Surface Materials, Accessories and Related Supplies, Chicago Department of Aviation, Specification Number 1274349 | F57: ROOT BROS MFG & SUPPLY CO | G57: 85 - CHICAGO DEPARTMENT OF AVIATION | H57: AVIATION | I57: 46220 | J57: 2023-05-26 | K57: 2081250 | L57: BID | M57: Yes | N57: COMMODITIES-AVIATION | O57: BLANKET | P57: BRIDGES, PORSHA D | Q57: 1148
A58: 385028 | B58: 346394 | C58: 653233 | D58: 1281675A | E58: ID Badging Supplies for O'Hare and Midway | F58: PLASTIC CARD SOLUTIONS, INC. | G58: 85 - CHICAGO DEPARTMENT OF AVIATION | H58: COMMODITIES | I58: 46176 | J58: 2025-06-17 | K58: 1701613.8 | L58: BID | M58: Yes | N58: COMMODITIES | O58: BLANKET | P58: BRIDGES, PORSHA D | Q58: 351
A59: 388839 | B59: 346792 | C59: 593511 | D59: 1296416 | E59: Professional Sewer Construction Management Engineering Services - Target Market (Task Order Services) | F59: THE RODERICK GROUP INC DBA ARDMORE RODERICK | G59: 88 - DEPARTMENT OF WATER MANAGEMENT | H59: ARCH & ENGINEERING | I59: 46191 | J59: 2024-12-04 | K59: 15000000 | L59: RFQ | M59: Yes | N59: ARCH/ENGINEERING | O59: BLANKET | P59: PESHOFF, NANCY R | Q59: 561
A60: 382539 | B60: 346793 | C60: 593511 | D60: 1296416 | E60: Professional Sewer Construction Management Engineering Services - Target Market (Task Order Services) | F60: COMPREHENSIVE CONSTRUCTION CONSULTING INC | G60: 88 - DEPARTMENT OF WATER MANAGEMENT | H60: ARCH & ENGINEERING | I60: 46191 | J60: 2024-12-04 | K60: 15000000 | L60: RFQ | M60: Yes | N60: ARCH/ENGINEERING | O60: BLANKET | P60: PESHOFF, NANCY R | Q60: 561
A61: 388840 | B61: 346794 | C61: 593511 | D61: 1296416 | E61: Professional Sewer Construction Management Engineering Services - Target Market (Task Order Services) | F61: SQN Associates, LLC | G61: 88 - DEPARTMENT OF WATER MANAGEMENT | H61: ARCH & ENGINEERING | I61: 46203 | J61: 2024-12-04 | K61: 15000000 | L61: RFQ | M61: Yes | N61: ARCH/ENGINEERING | O61: BLANKET | P61: PESHOFF, NANCY R | Q61: 573
A62: 388833 | B62: 346795 | C62: 593511 | D62: 1296416 | E62: Professional Sewer Construction Management Engineering Services - Target Market (Task Order Services) | F62: D'ESCOTO, INC. | G62: 88 - DEPARTMENT OF WATER MANAGEMENT | H62: ARCH & ENGINEERING | I62: 46191 | J62: 2024-12-04 | K62: 15000000 | L62: RFQ | M62: Yes | N62: ARCH/ENGINEERING | O62: BLANKET | P62: PESHOFF, NANCY R | Q62: 561
A63: 388841 | B63: 346796 | C63: 593511 | D63: 1296416 | E63: Professional Sewer Construction Management Engineering Services - Target Market (Task Order Services) | F63: TERRA ENGINEERING LTD | G63: 88 - DEPARTMENT OF WATER MANAGEMENT | H63: ARCH & ENGINEERING | I63: 46203 | J63: 2024-12-04 | K63: 15000000 | L63: RFQ | M63: Yes | N63: ARCH/ENGINEERING | O63: BLANKET | P63: PESHOFF, NANCY R | Q63: 573
A64: 388832 | B64: 346797 | C64: 593511 | D64: 1296416 | E64: Professional Sewer Construction Management Engineering Services - Target Market (Task Order Services) | F64: D.B. STERLIN CONSULTANTS, INC. | G64: 88 - DEPARTMENT OF WATER MANAGEMENT | H64: ARCH & ENGINEERING | I64: 46191 | J64: 2024-12-04 | K64: 15000000 | L64: RFQ | M64: Yes | N64: ARCH/ENGINEERING | O64: BLANKET | P64: PESHOFF, NANCY R | Q64: 561
A65: 388838 | B65: 346798 | C65: 593511 | D65: 1296416 | E65: Professional Sewer Construction Management Engineering Services - Target Market (Task Order Services) | F65: PDF Engineering llc | G65: 88 - DEPARTMENT OF WATER MANAGEMENT | H65: ARCH & ENGINEERING | I65: 46191 | J65: 2024-12-04 | K65: 15000000 | L65: RFQ | M65: Yes | N65: ARCH/ENGINEERING | O65: BLANKET | P65: PESHOFF, NANCY R | Q65: 561
A66: 388837 | B66: 346799 | C66: 593511 | D66: 1296416 | E66: Professional Sewer Construction Management Engineering Services - Target Market (Task Order Services) | F66: MILHOUSE ENGINEERING & CONSTRUCTION INC. | G66: 88 - DEPARTMENT OF WATER MANAGEMENT | H66: ARCH & ENGINEERING | I66: 46191 | J66: 2024-12-04 | K66: 15000000 | L66: RFQ | M66: Yes | N66: ARCH/ENGINEERING | O66: BLANKET | P66: PESHOFF, NANCY R | Q66: 561
A67: 388835 | B67: 346800 | C67: 593511 | D67: 1296416 | E67: Professional Sewer Construction Management Engineering Services - Target Market (Task Order Services) | F67: GSG CONSULTANTS, INC. | G67: 88 - DEPARTMENT OF WATER MANAGEMENT | H67: ARCH & ENGINEERING | I67: 46191 | J67: 2024-12-04 | K67: 15000000 | L67: RFQ | M67: Yes | N67: ARCH/ENGINEERING | O67: BLANKET | P67: PESHOFF, NANCY R | Q67: 561
A68: 388836 | B68: 346801 | C68: 593511 | D68: 1296416 | E68: Professional Sewer Construction Management Engineering Services - Target Market (Task Order Services) | F68: INFRASTRUCTURE ENGINEERING INC | G68: 88 - DEPARTMENT OF WATER MANAGEMENT | H68: ARCH & ENGINEERING | I68: 46191 | J68: 2024-12-04 | K68: 15000000 | L68: RFQ | M68: Yes | N68: ARCH/ENGINEERING | O68: BLANKET | P68: PESHOFF, NANCY R | Q68: 561
A69: 388834 | B69: 346802 | C69: 593511 | D69: 1296416 | E69: Professional Sewer Construction Management Engineering Services - Target Market (Task Order Services) | F69: ENVIRONMENTAL DESIGN INT'L | G69: 88 - DEPARTMENT OF WATER MANAGEMENT | H69: ARCH & ENGINEERING | I69: 46191 | J69: 2024-12-04 | K69: 15000000 | L69: RFQ | M69: Yes | N69: ARCH/ENGINEERING | O69: BLANKET | P69: PESHOFF, NANCY R | Q69: 561
A70: 388646 | B70: 346937 | C70: 608211 | D70: 1301822 | E70: OSHKOSH STRIKER AIRCRAFT RESCUE AND FIRE FIGHTING ("ARFF") VEHICLES (SPEC #1301822) Contract No. 346937 is hereby issued in replacement of Contract No. 341812 for administrative purposes, as the original contract did not include line items | F70: PIERCE MANUFACTURING INC | G70: 85 - CHICAGO DEPARTMENT OF AVIATION | H70: VEHICLES & HEAVY EQUIPMENT | I70: 46126 | J70: 2024-06-25 | K70: 11112382 | L70: REFERENCE CONTRACT | M70: No | N70: VEHICLES/HEAVY EQUIPMENT (CAPITAL) | O70: BLANKET | P70: DUKE, KARL D | Q70: 658
A71: 388647 | B71: 347257 | D71: 132865 | E71: Oracle Software Renewal for the period of 9/1/2024 through 08/31/2025 for a total cost of $178,650.71- and one-year software update license & Support for Multitenant-Processor for the period of 9/1/2025 through 8/31/2026 | F71: Mythics, LLC | G71: 85 - CHICAGO DEPARTMENT OF AVIATION | H71: PROFESSIONAL SERVICES | I71: 46120 | J71: 2026-04-07 | K71: 197323.89 | L71: JOINT PURCHASE | M71: No | N71: SOFTWARE | O71: STANDARD | P71: KNIGHT JR, DERRICK | Q71: 1
A72: 388766 | B72: 347319 | D72: 579313 | E72: Transfer from PO 100786 Phase 1 & Phase 2 Design Engineering & Architectural Services for Replacement of the State/Lake Loop Elevated CTA Station | F72: GFT Infrastructure, Inc. | G72: 84 - CHICAGO DEPARTMENT OF TRANSPORTATION | H72: ARCH & ENGINEERING | I72: 46142 | J72: 2026-04-29 | K72: 2 | L72: CONTRACT ASSIGNMENT/TRANSFER | M72: No | N72: ARCH/ENGINEERING | O72: BLANKET | P72: CORTES, JEZIEEL T | Q72: 1
A73: 389107 | B73: 347622 | D73: 781131 | E73: PICK-UP TRUCKS: GROUP A (FULL SIZE), GROUP B (MID-SIZE) AND GROUP C (PURSUIT RATED) (Transfer from PO 115511) | F73: ILF1, LLC dba ELMHURST FORD | G73: 38 - DEPARTMENT OF FLEET AND FACILITY MANAGEMENT | H73: VEHICLES & HEAVY EQUIPMENT | I73: 46183 | J73: 2026-06-09 | K73: 18299496 | L73: CONTRACT ASSIGNMENT/TRANSFER | M73: No | N73: VEHICLES/HEAVY EQUIPMENT (CAPITAL) | O73: BLANKET | P73: PIPERCANON, KIMBERLY | Q73: 1
A74: 388126 | B74: 347805 | C74: 697361 | D74: 1336819 | E74: Hansen and Infor Public Sector Software Maintenance and Support Services and Optional Project Services | F74: INFOR PUBLIC SECTOR INC | G74: 06 - DEPARTMENT OF TECHNOLOGY AND INNOVATION | H74: PROFESSIONAL SERVICES | I74: 46132 | J74: 2026-02-10 | K74: 18892897 | L74: SOLE SOURCE | M74: No | N74: PRO SERV CONSULTING $250,000orABOVE | O74: BLANKET | P74: CALLAHAN, PATRICK M | Q74: 69
A75: 388652 | B75: 348043 | C75: 721234 | D75: 450998 | E75: DLT Quote #5345877 for Oracle | F75: DLT SOLUTIONS LLC | G75: 06 - DEPARTMENT OF TECHNOLOGY AND INNOVATION | H75: PROFESSIONAL SERVICES | I75: 46153 | J75: 2026-04-08 | K75: 1231661.4 | L75: JOINT PURCHASE | M75: No | N75: SOFTWARE | O75: STANDARD | P75: CORTES, ANN C | Q75: 33
A76: 388635 | B76: 348048 | C76: 722388 | D76: 450998 | E76: DLT Quote #5286479 for Oracle. | F76: DLT SOLUTIONS LLC | G76: 06 - DEPARTMENT OF TECHNOLOGY AND INNOVATION | H76: PROFESSIONAL SERVICES | I76: 46153 | J76: 2026-04-03 | K76: 5941260 | L76: JOINT PURCHASE | M76: No | N76: SOFTWARE | O76: STANDARD | P76: CORTES, ANN C | Q76: 38
A77: 383493 | B77: 348918 | C77: 615702 | D77: 1304275 | E77: 1304275: Protective Footwear with Mobile Shoe Unit | F77: HY TEST SAFETY SHOE SERVICE | G77: 38 - DEPARTMENT OF FLEET AND FACILITY MANAGEMENT | H77: COMMODITIES | I77: 46203 | J77: 2025-02-26 | K77: 817320 | L77: BID | M77: Yes | N77: COMMODITIES | O77: BLANKET | P77: POLK-STAMPS, MELANIE L | Q77: 489
A78: 381051 | B78: 348927 | C78: 613315 | D78: 1303484 | E78: 1303484: Rental and Maintenance of Portable Chemical Toilets, Sinks, Waste Water Barrels, Portable Waterless Hand Sanitizer Dispensers, Fresh Water Trailer and Portable Showers (Groups) | F78: Service Sanitation Inc. | G78: 23 - DEPARTMENT OF CULTURAL AFFAIRS AND SPECIAL EVENTS | H78: WORK SERVICES | I78: 46203 | J78: 2024-08-06 | K78: 11251262 | L78: BID | M78: Yes | N78: WORK SERVICES / FACILITIES MAINT. | O78: BLANKET | P78: POLK-STAMPS, MELANIE L | Q78: 693
A79: 386230 | B79: 349635 | C79: 686932 | D79: 1201402 | E79: 1201402: MILWAUKEE AVENUE SECTION 5 IMPROVEMENTS Logan Square Blue Line Station Headhouse Reconstruction | F79: FH PASCHEN SN NIELSEN & ASSOCIATES LLC | G79: 84 - CHICAGO DEPARTMENT OF TRANSPORTATION | H79: CONSTRUCTION | I79: 46156 | J79: 2025-09-03 | K79: 19736000 | L79: BID | M79: Yes | N79: CONSTRUCTION-LARGE $3MILLIONorABOVE | O79: STANDARD | P79: BROWNLEE, OSHA | Q79: 253
A80: 386113 | B80: 349808 | C80: 675350 | D80: 1327954 | E80: (SPEC 1327954) Taxiways S, S1, S2, and S3 Rehabilitation at O'Hare International Airport | F80: PLOTE CONSTRUCTION, INC. | G80: 85 - CHICAGO DEPARTMENT OF AVIATION | H80: AVIATION | I80: 46176 | J80: 2025-06-30 | K80: 30283769 | L80: BID | M80: Yes | N80: CONSTRUCTION-AVIATION | O80: STANDARD | P80: DUKE, KARL D | Q80: 338
A81: 388769 | B81: 350300 | D81: 1131763 | E81: TRANSFER FROM PO 200123 - PROFESSIONAL CONSTRUCTION ENGINEERING SERVICES FOR CITY-WIDE CDOT ROADWAY AND BRIDGE PROJECTS - TASK ORDER SERVICES- MASTER CONSULTING AGREEMENTS | F81: GFT Infrastructure, Inc. | G81: 84 - CHICAGO DEPARTMENT OF TRANSPORTATION | H81: ARCH & ENGINEERING | I81: 46141 | J81: 2026-04-29 | K81: 16141254 | L81: CONTRACT ASSIGNMENT/TRANSFER | M81: No | N81: ARCH/ENGINEERING | O81: BLANKET | P81: CORTES, JEZIEEL T
A82: 388105 | B82: 351523 | C82: 711524 | D82: 1342948 | E82: Residential Sound Insulation Program Odor Mitigation Phase 1 - Spec 1342948 | F82: BLINDERMAN CONSTRUCTION COMPANY INC | G82: 85 - CHICAGO DEPARTMENT OF AVIATION | H82: AVIATION | I82: 46168 | J82: 2026-01-29 | K82: 17589950 | L82: BID | M82: Yes | N82: CONSTRUCTION-AVIATION | O82: STANDARD | P82: MAGNO, THOMAS | Q82: 117
A83: 388911 | B83: 351608 | D83: 1197349 | E83: TRANSFER FROM PO 282542 - Professional Design Engineering Services for the Management of City's Underground Infrastructure | F83: GFT Infrastructure, Inc. | G83: 84 - CHICAGO DEPARTMENT OF TRANSPORTATION | H83: ARCH & ENGINEERING | I83: 46157 | J83: 2026-05-14 | K83: 13063063 | L83: CONTRACT ASSIGNMENT/TRANSFER | M83: No | N83: ARCH/ENGINEERING | O83: BLANKET | P83: CORTES, JEZIEEL T | Q83: 1
A84: 381309 | B84: 351919 | C84: 607558 | D84: 1301356 | E84: Meteorological Services | F84: MURRAY & TRETTEL INC | G84: 85 - CHICAGO DEPARTMENT OF AVIATION | H84: AVIATION | I84: 46229 | J84: 2024-06-21 | K84: 189900 | L84: BID | M84: Yes | N84: WORK SERV-AVIATION | O84: BLANKET | P84: MERRICK, TOBY | Q84: 765
A85: 388914 | B85: 352124 | D85: 1204697 | E85: TRANSFER FROM PO 223980 - MASTER TASK ORDER CONTRACT PROFESSIONAL DESIGN ENGINEERING SERVICES FOR GROUPS 2 THROUGH 4 PHASE I AND II TASK ORDER SERVICES, GROUPS - 2: STRUCTURES (MOVABLE, 3: ROADWAY & 4: TRAFFIC SIGNALS & ROADWAY LIGHTING | F85: GFT Infrastructure, Inc. | G85: 84 - CHICAGO DEPARTMENT OF TRANSPORTATION | H85: ARCH & ENGINEERING | I85: 46157 | J85: 2026-05-14 | K85: 6848789.9 | L85: CONTRACT ASSIGNMENT/TRANSFER | M85: No | N85: ARCH/ENGINEERING | O85: BLANKET | P85: CORTES, JEZIEEL T | Q85: 1
A86: 388920 | B86: 352557 | C86: 730967 | D86: 450998 | E86: DLT Quote# 5351341 for Oracle renewal | F86: DLT SOLUTIONS LLC | G86: 06 - DEPARTMENT OF TECHNOLOGY AND INNOVATION | H86: PROFESSIONAL SERVICES | I86: 46209 | J86: 2026-05-15 | K86: 43089.55 | L86: JOINT PURCHASE | M86: No | N86: SOFTWARE | O86: STANDARD | P86: CORTES, ANN C | Q86: 52
A87: 388922 | B87: 352601 | C87: 730941 | D87: 450998 | E87: DLT Quote# 5355189 for software update license and support. | F87: DLT SOLUTIONS LLC | G87: 06 - DEPARTMENT OF TECHNOLOGY AND INNOVATION | H87: PROFESSIONAL SERVICES | I87: 46209 | J87: 2026-05-15 | K87: 30333.8 | L87: JOINT PURCHASE | M87: No | N87: SOFTWARE | O87: STANDARD | P87: CORTES, ANN C | Q87: 52
A88: 388921 | B88: 352604 | C88: 730929 | D88: 450998 | E88: DLT Quote# 5366584 for enterprise technical support fees | F88: DLT SOLUTIONS LLC | G88: 06 - DEPARTMENT OF TECHNOLOGY AND INNOVATION | H88: PROFESSIONAL SERVICES | I88: 46191 | J88: 2026-05-15 | K88: 36295.37 | L88: JOINT PURCHASE | M88: No | N88: SOFTWARE | O88: STANDARD | P88: CORTES, ANN C | Q88: 34
A89: 388923 | B89: 352606 | C89: 730961 | D89: 450998 | E89: DLT Quote# 5354528 Oracle renewal | F89: DLT SOLUTIONS LLC | G89: 06 - DEPARTMENT OF TECHNOLOGY AND INNOVATION | H89: PROFESSIONAL SERVICES | I89: 46209 | J89: 2026-05-15 | K89: 274584.38 | L89: JOINT PURCHASE | M89: No | N89: SOFTWARE | O89: STANDARD | P89: CORTES, ANN C | Q89: 52
A90: 388927 | B90: 352841 | C90: 730950 | D90: 450998 | E90: DLT Quote# 5351385 for Oracle enterprise software and support | F90: DLT SOLUTIONS LLC | G90: 06 - DEPARTMENT OF TECHNOLOGY AND INNOVATION | H90: PROFESSIONAL SERVICES | I90: 46191 | J90: 2026-05-18 | K90: 854301.3 | L90: JOINT PURCHASE | M90: No | N90: SOFTWARE | O90: STANDARD | P90: CORTES, ANN C | Q90: 31
A91: 388989 | B91: 353311 | D91: 140827 | E91: TRANSFER FROM PO 241983 - PROFESSIONAL SEWER CONSTRUCTION ENGINEERING SERVICES | F91: GFT Infrastructure, Inc. | G91: 88 - DEPARTMENT OF WATER MANAGEMENT | H91: ARCH & ENGINEERING | I91: 46170 | J91: 2026-05-26 | K91: 2828363.2 | L91: CONTRACT ASSIGNMENT/TRANSFER | M91: No | N91: ARCH/ENGINEERING | O91: BLANKET | P91: CORTES, JEZIEEL T | Q91: 2
A92: 388990 | B92: 353314 | D92: 140827 | E92: TRANSFER FROM PO 71114 - PROFESSIONAL SEWER CONSTRUCTION ENGINEERING SERVICES | F92: GFT Infrastructure, Inc. | G92: 88 - DEPARTMENT OF WATER MANAGEMENT | H92: ARCH & ENGINEERING | I92: 46168 | J92: 2026-05-26 | K92: 7465933.8 | L92: CONTRACT ASSIGNMENT/TRANSFER | M92: No | N92: ARCH/ENGINEERING | O92: BLANKET | P92: CORTES, JEZIEEL T
A93: 386787 | B93: 353395 | C93: 686037 | D93: 1332122 | E93: Taxiway Y South, Y3 & Y4 Pavement Rehabilitation | F93: WALSH CONSTRUCTION COMPANY II, LLC. | G93: 85 - CHICAGO DEPARTMENT OF AVIATION | H93: AVIATION | I93: 46203 | J93: 2025-08-27 | K93: 21154050 | L93: BID | M93: Yes | N93: CONSTRUCTION-AVIATION | O93: STANDARD | P93: MAGNO, THOMAS | Q93: 307
A94: 382207 | B94: 353680 | C94: 619968 | D94: 1305815 | E94: Spec 1305815: PROMOTIONAL PRODUCTS WEARABLES AND ACCESSORIES - TARGET MARKET | F94: SILK SCREEN EXPRESS, INC. | G94: 57 - CHICAGO POLICE DEPARTMENT | H94: COMMODITIES | I94: 46241 | J94: 2024-11-07 | K94: 8356754 | L94: BID | M94: Yes | N94: COMMODITIES | O94: BLANKET | P94: HARRISON-BONNER, KENYA D | Q94: 638
A95: 389292 | B95: 355260 | D95: 135025 | E95: (TRANSFER FROM PO 34921) IMPOUND FACILITY MANAGEMENT, BOOT RELEASE, TOWING AND RELATED SERVICES | F95: URT United Road Towing Inc. | G95: 81 - DEPARTMENT OF STREETS AND SANITATION | H95: PROFESSIONAL SERVICES | I95: 46231 | J95: 2026-07-01 | K95: 16099245 | L95: CONTRACT ASSIGNMENT/TRANSFER | M95: No | N95: PRO SERV CONSULTING $250,000orABOVE | O95: BLANKET | P95: CALLAHAN, PATRICK M | Q95: 27
A96: 389247 | B96: 355559 | C96: 593509 | D96: 1296415 | E96: Professional Sewer Construction Management Engineering Services - non-Target Market (Task Order Services) | F96: WSP USA INC. | G96: 88 - DEPARTMENT OF WATER MANAGEMENT | H96: ARCH & ENGINEERING | I96: 46245 | J96: 2024-12-04 | K96: 15000000 | L96: RFQ | M96: Yes | N96: ARCH/ENGINEERING | O96: BLANKET | P96: PESHOFF, NANCY R | Q96: 615
A97: 389238 | B97: 355560 | C97: 593509 | D97: 1296415 | E97: Professional Sewer Construction Management Engineering Services - non-Target Market (Task Order Services) | F97: COTTER CONSULTING, INC. | G97: 88 - DEPARTMENT OF WATER MANAGEMENT | H97: ARCH & ENGINEERING | I97: 46245 | J97: 2024-12-04 | K97: 15000000 | L97: RFQ | M97: Yes | N97: ARCH/ENGINEERING | O97: BLANKET | P97: PESHOFF, NANCY R | Q97: 615
A98: 382535 | B98: 355561 | C98: 593509 | D98: 1296415 | E98: Professional Sewer Construction Management Engineering Services - non-Target Market (Task Order Services) | F98: ALFRED BENESCH & CO | G98: 88 - DEPARTMENT OF WATER MANAGEMENT | H98: ARCH & ENGINEERING | I98: 46245 | J98: 2024-12-04 | K98: 15000000 | L98: RFQ | M98: Yes | N98: ARCH/ENGINEERING | O98: BLANKET | P98: PESHOFF, NANCY R | Q98: 615
A99: 389244 | B99: 355564 | C99: 593509 | D99: 1296415 | E99: Professional Sewer Construction Management Engineering Services - non-Target Market (Task Order Services) | F99: THE RODERICK GROUP INC DBA ARDMORE RODERICK | G99: 88 - DEPARTMENT OF WATER MANAGEMENT | H99: ARCH & ENGINEERING | I99: 46245 | J99: 2024-12-04 | K99: 15000000 | L99: RFQ | M99: Yes | N99: ARCH/ENGINEERING | O99: BLANKET | P99: PESHOFF, NANCY R | Q99: 615
A100: 389093 | B100: 356057 | C100: 734373 | D100: 1318223 | E100: (Spec 1318223) Operation and Maintenance of the Airport Transit System (ATS) at Chicago O'Hare International Airport | F100: AOR TRANSIT | G100: 85 - CHICAGO DEPARTMENT OF AVIATION | H100: PROFESSIONAL SERVICES | I100: 46216 | J100: 2026-06-04 | K100: 1050000000 | L100: SOLE SOURCE | M100: No | N100: PRO SERV-AVIATION | O100: BLANKET | P100: DUKE, KARL D | Q100: 39
A101: 389274 | B101: 357467 | C101: 738998 | D101: 1297152 | E101: Ring Tunnel Exhaust System, Emergency Hazardous Gas, and Smoke Evacuation at Chicago O'Hare Int'l Airport, Spec 1297152, (MBI) Mid-Sized Business Enterprise | F101: BLINDERMAN CONSTRUCTION COMPANY INC | G101: 85 - CHICAGO DEPARTMENT OF AVIATION | H101: AVIATION | I101: 46231 | J101: 2026-07-01 | K101: 18797000 | L101: BID | M101: Yes | N101: CONSTRUCTION-AVIATION | O101: STANDARD | P101: MAGNO, THOMAS | Q101: 27
